Workbook

Sheet Order Detail
A1: orderid | B1: productid | C1: unitprice | D1: qty | E1: discount | F1: Customer Name | G1: Column Name2 | H1: Employee Name | I1: Employee Region | J1: Product Name | K1: Product Category | L1: orderdate | M1: shippeddate | N1: Shipping Company | O1: shipname | P1: shipcountry | Q1: Supplying Company | R1: Supplier Country | S1: Freight Category | T1: Revenue | U1: Data Note
A2: 10248 | B2: 11 | C2: 14 | D2: 12 | E2: 0 | F2: =IFERROR(VLOOKUP(VLOOKUP(A2,'Sales Order'!A:B,2,FALSE),Customer!A:C,3,FALSE),"Not Specified") -> Not Specified | G2: =SUBSTITUTE(F2,",","",1) -> Not Specified | H2: =IFERROR(VLOOKUP(VLOOKUP(A2,'Sales Order'!A:C,3,FALSE),Employee!A:E,5,FALSE)&" "&VLOOKUP(VLOOKUP(A2,'Sales Order'!A:C,3,FALSE),Employee!A:C,3,FALSE)&" "&VLOOKUP(VLOOKUP(A2,'Sales Order'!A:C,3,FALSE),Employee!A:B,2,FALSE),"Not Specified") -> Not Specified | I2: =IFERROR(VLOOKUP(VLOOKUP(A2,'Sales Order'!A:C,3,FALSE),Employee!A:J,10,FALSE),"Not Specified") -> Not Specified | J2: =VLOOKUP(B2,Product!A:B,2,FALSE) -> Product QMVUN | K2: =VLOOKUP(VLOOKUP(B2,Product!A:D,4,FALSE),Category!A:B,2,FALSE) -> Dairy Product | M2: =IFERROR(VLOOKUP(A2,'Sales Order'!A:F,6,FALSE),"") | N2: =IFERROR(VLOOKUP(VLOOKUP(A2,'Sales Order'!A:G,7,FALSE),Shipper!A:B,2,FALSE),"Not Specified") -> Not Specified | O2: =IFERROR(VLOOKUP(A2,'Sales Order'!A:I,9,FALSE),"Not Specified") -> Not Specified | P2: =IFERROR(VLOOKUP(A2,'Sales Order'!A:N,14,FALSE),"Not Specified") -> Not Specified | Q2: =VLOOKUP(VLOOKUP(B2,Product!A:C,3,FALSE),Supplier!A:B,2,FALSE) -> Supplier EQPNC | R2: =VLOOKUP(VLOOKUP(B2,Product!A:C,3,FALSE),Supplier!A:I,9,FALSE) -> Spain | S2: =IFERROR(IF(VLOOKUP(A2,'Sales Order'!A:H,8,FALSE)>100,"High Freight","Low Freight"),"Not Specified") -> Not Specified | T2: =C2*D2*(1-E2) -> 168 | U2: Order 10248 absent from Sales Order; orderdate not available
A3: 10248 | B3: 42 | C3: 9.8 | D3: 10 | E3: 0 | F3: =IFERROR(VLOOKUP(VLOOKUP(A3,'Sales Order'!A:B,2,FALSE),Customer!A:C,3,FALSE),"Not Specified") -> Not Specified | G3: =SUBSTITUTE(F3,",","",1) -> Not Specified | H3: =IFERROR(VLOOKUP(VLOOKUP(A3,'Sales Order'!A:C,3,FALSE),Employee!A:E,5,FALSE)&" "&VLOOKUP(VLOOKUP(A3,'Sales Order'!A:C,3,FALSE),Employee!A:C,3,FALSE)&" "&VLOOKUP(VLOOKUP(A3,'Sales Order'!A:C,3,FALSE),Employee!A:B,2,FALSE),"Not Specified") -> Not Specified | I3: =IFERROR(VLOOKUP(VLOOKUP(A3,'Sales Order'!A:C,3,FALSE),Employee!A:J,10,FALSE),"Not Specified") -> Not Specified | J3: =VLOOKUP(B3,Product!A:B,2,FALSE) -> Product RJVNM | K3: =VLOOKUP(VLOOKUP(B3,Product!A:D,4,FALSE),Category!A:B,2,FALSE) -> Grains/Cereals | M3: =IFERROR(VLOOKUP(A3,'Sales Order'!A:F,6,FALSE),"") | N3: =IFERROR(VLOOKUP(VLOOKUP(A3,'Sales Order'!A:G,7,FALSE),Shipper!A:B,2,FALSE),"Not Specified") -> Not Specified | O3: =IFERROR(VLOOKUP(A3,'Sales Order'!A:I,9,FALSE),"Not Specified") -> Not Specified | P3: =IFERROR(VLOOKUP(A3,'Sales Order'!A:N,14,FALSE),"Not Specified") -> Not Specified | Q3: =VLOOKUP(VLOOKUP(B3,Product!A:C,3,FALSE),Supplier!A:B,2,FALSE) -> Supplier CIYNM | R3: =VLOOKUP(VLOOKUP(B3,Product!A:C,3,FALSE),Supplier!A:I,9,FALSE) -> Singapore | S3: =IFERROR(IF(VLOOKUP(A3,'Sales Order'!A:H,8,FALSE)>100,"High Freight","Low Freight"),"Not Specified") -> Not Specified | T3: =C3*D3*(1-E3) -> 98 | U3: Order 10248 absent from Sales Order; orderdate not available
A4: 10248 | B4: 72 | C4: 34.8 | D4: 5 | E4: 0 | F4: =IFERROR(VLOOKUP(VLOOKUP(A4,'Sales Order'!A:B,2,FALSE),Customer!A:C,3,FALSE),"Not Specified") -> Not Specified | G4: =SUBSTITUTE(F4,",","",1) -> Not Specified | H4: =IFERROR(VLOOKUP(VLOOKUP(A4,'Sales Order'!A:C,3,FALSE),Employee!A:E,5,FALSE)&" "&VLOOKUP(VLOOKUP(A4,'Sales Order'!A:C,3,FALSE),Employee!A:C,3,FALSE)&" "&VLOOKUP(VLOOKUP(A4,'Sales Order'!A:C,3,FALSE),Employee!A:B,2,FALSE),"Not Specified") -> Not Specified | I4: =IFERROR(VLOOKUP(VLOOKUP(A4,'Sales Order'!A:C,3,FALSE),Employee!A:J,10,FALSE),"Not Specified") -> Not Specified | J4: =VLOOKUP(B4,Product!A:B,2,FALSE) -> Product GEEOO | K4: =VLOOKUP(VLOOKUP(B4,Product!A:D,4,FALSE),Category!A:B,2,FALSE) -> Dairy Product | M4: =IFERROR(VLOOKUP(A4,'Sales Order'!A:F,6,FALSE),"") | N4: =IFERROR(VLOOKUP(VLOOKUP(A4,'Sales Order'!A:G,7,FALSE),Shipper!A:B,2,FALSE),"Not Specified") -> Not Specified | O4: =IFERROR(VLOOKUP(A4,'Sales Order'!A:I,9,FALSE),"Not Specified") -> Not Specified | P4: =IFERROR(VLOOKUP(A4,'Sales Order'!A:N,14,FALSE),"Not Specified") -> Not Specified | Q4: =VLOOKUP(VLOOKUP(B4,Product!A:C,3,FALSE),Supplier!A:B,2,FALSE) -> Supplier KEREV | R4: =VLOOKUP(VLOOKUP(B4,Product!A:C,3,FALSE),Supplier!A:I,9,FALSE) -> Italy | S4: =IFERROR(IF(VLOOKUP(A4,'Sales Order'!A:H,8,FALSE)>100,"High Freight","Low Freight"),"Not Specified") -> Not Specified | T4: =C4*D4*(1-E4) -> 174 | U4: Order 10248 absent from Sales Order; orderdate not available
A5: 10249 | B5: 14 | C5: 18.6 | D5: 9 | E5: 0 | F5: =IFERROR(VLOOKUP(VLOOKUP(A5,'Sales Order'!A:B,2,FALSE),Customer!A:C,3,FALSE),"Not Specified") -> Not Specified | G5: =SUBSTITUTE(F5,",","",1) -> Not Specified | H5: =IFERROR(VLOOKUP(VLOOKUP(A5,'Sales Order'!A:C,3,FALSE),Employee!A:E,5,FALSE)&" "&VLOOKUP(VLOOKUP(A5,'Sales Order'!A:C,3,FALSE),Employee!A:C,3,FALSE)&" "&VLOOKUP(VLOOKUP(A5,'Sales Order'!A:C,3,FALSE),Employee!A:B,2,FALSE),"Not Specified") -> Not Specified | I5: =IFERROR(VLOOKUP(VLOOKUP(A5,'Sales Order'!A:C,3,FALSE),Employee!A:J,10,FALSE),"Not Specified") -> Not Specified | J5: =VLOOKUP(B5,Product!A:B,2,FALSE) -> Product PWCJB | K5: =VLOOKUP(VLOOKUP(B5,Product!A:D,4,FALSE),Category!A:B,2,FALSE) -> Produce | M5: =IFERROR(VLOOKUP(A5,'Sales Order'!A:F,6,FALSE),"") | N5: =IFERROR(VLOOKUP(VLOOKUP(A5,'Sales Order'!A:G,7,FALSE),Shipper!A:B,2,FALSE),"Not Specified") -> Not Specified | O5: =IFERROR(VLOOKUP(A5,'Sales Order'!A:I,9,FALSE),"Not Specified") -> Not Specified | P5: =IFERROR(VLOOKUP(A5,'Sales Order'!A:N,14,FALSE),"Not Specified") -> Not Specified | Q5: =VLOOKUP(VLOOKUP(B5,Product!A:C,3,FALSE),Supplier!A:B,2,FALSE) -> Supplier QWUSF | R5: =VLOOKUP(VLOOKUP(B5,Product!A:C,3,FALSE),Supplier!A:I,9,FALSE) -> Japan | S5: =IFERROR(IF(VLOOKUP(A5,'Sales Order'!A:H,8,FALSE)>100,"High Freight","Low Freight"),"Not Specified") -> Not Specified | T5: =C5*D5*(1-E5) -> 167.4 | U5: Order 10249 absent from Sales Order; orderdate not available
A6: 10249 | B6: 51 | C6: 42.4 | D6: 40 | E6: 0 | F6: =IFERROR(VLOOKUP(VLOOKUP(A6,'Sales Order'!A:B,2,FALSE),Customer!A:C,3,FALSE),"Not Specified") -> Not Specified | G6: =SUBSTITUTE(F6,",","",1) -> Not Specified | H6: =IFERROR(VLOOKUP(VLOOKUP(A6,'Sales Order'!A:C,3,FALSE),Employee!A:E,5,FALSE)&" "&VLOOKUP(VLOOKUP(A6,'Sales Order'!A:C,3,FALSE),Employee!A:C,3,FALSE)&" "&VLOOKUP(VLOOKUP(A6,'Sales Order'!A:C,3,FALSE),Employee!A:B,2,FALSE),"Not Specified") -> Not Specified | I6: =IFERROR(VLOOKUP(VLOOKUP(A6,'Sales Order'!A:C,3,FALSE),Employee!A:J,10,FALSE),"Not Specified") -> Not Specified | J6: =VLOOKUP(B6,Product!A:B,2,FALSE) -> Product APITJ | K6: =VLOOKUP(VLOOKUP(B6,Product!A:D,4,FALSE),Category!A:B,2,FALSE) -> Produce | M6: =IFERROR(VLOOKUP(A6,'Sales Order'!A:F,6,FALSE),"") | N6: =IFERROR(VLOOKUP(VLOOKUP(A6,'Sales Order'!A:G,7,FALSE),Shipper!A:B,2,FALSE),"Not Specified") -> Not Specified | O6: =IFERROR(VLOOKUP(A6,'Sales Order'!A:I,9,FALSE),"Not Specified") -> Not Specified | P6: =IFERROR(VLOOKUP(A6,'Sales Order'!A:N,14,FALSE),"Not Specified") -> Not Specified | Q6: =VLOOKUP(VLOOKUP(B6,Product!A:C,3,FALSE),Supplier!A:B,2,FALSE) -> Supplier JNNES | R6: =VLOOKUP(VLOOKUP(B6,Product!A:C,3,FALSE),Supplier!A:I,9,FALSE) -> Australia | S6: =IFERROR(IF(VLOOKUP(A6,'Sales Order'!A:H,8,FALSE)>100,"High Freight","Low Freight"),"Not Specified") -> Not Specified | T6: =C6*D6*(1-E6) -> 1696 | U6: Order 10249 absent from Sales Order; orderdate not available
A7: 10250 | B7: 41 | C7: 7.7 | D7: 10 | E7: 0 | F7: =IFERROR(VLOOKUP(VLOOKUP(A7,'Sales Order'!A:B,2,FALSE),Customer!A:C,3,FALSE),"Not Specified") -> Cohen, Shy | G7: =SUBSTITUTE(F7,",","",1) -> Cohen Shy | H7: =IFERROR(VLOOKUP(VLOOKUP(A7,'Sales Order'!A:C,3,FALSE),Employee!A:E,5,FALSE)&" "&VLOOKUP(VLOOKUP(A7,'Sales Order'!A:C,3,FALSE),Employee!A:C,3,FALSE)&" "&VLOOKUP(VLOOKUP(A7,'Sales Order'!A:C,3,FALSE),Employee!A:B,2,FALSE),"Not Specified") -> Mrs. Yael Peled | I7: =IFERROR(VLOOKUP(VLOOKUP(A7,'Sales Order'!A:C,3,FALSE),Employee!A:J,10,FALSE),"Not Specified") -> WA | J7: =VLOOKUP(B7,Product!A:B,2,FALSE) -> Product TTEEX | K7: =VLOOKUP(VLOOKUP(B7,Product!A:D,4,FALSE),Category!A:B,2,FALSE) -> Seafood | L7: =IFERROR(VLOOKUP(A7,'Sales Order'!A:D,4,FALSE),"") -> 38906 | M7: =IFERROR(VLOOKUP(A7,'Sales Order'!A:F,6,FALSE),"") -> 38910 | N7: =IFERROR(VLOOKUP(VLOOKUP(A7,'Sales Order'!A:G,7,FALSE),Shipper!A:B,2,FALSE),"Not Specified") -> Shipper ETYNR | O7: =IFERROR(VLOOKUP(A7,'Sales Order'!A:I,9,FALSE),"Not Specified") -> Destination SCQXA | P7: =IFERROR(VLOOKUP(A7,'Sales Order'!A:N,14,FALSE),"Not Specified") -> Brazil | Q7: =VLOOKUP(VLOOKUP(B7,Product!A:C,3,FALSE),Supplier!A:B,2,FALSE) -> Supplier JDNUG | R7: =VLOOKUP(VLOOKUP(B7,Product!A:C,3,FALSE),Supplier!A:I,9,FALSE) -> USA | S7: =IFERROR(IF(VLOOKUP(A7,'Sales Order'!A:H,8,FALSE)>100,"High Freight","Low Freight"),"Not Specified") -> Low Freight | T7: =C7*D7*(1-E7) -> 77
A8: 10250 | B8: 51 | C8: 42.4 | D8: 35 | E8: 0.15 | F8: =IFERROR(VLOOKUP(VLOOKUP(A8,'Sales Order'!A:B,2,FALSE),Customer!A:C,3,FALSE),"Not Specified") -> Cohen, Shy | G8: =SUBSTITUTE(F8,",","",1) -> Cohen Shy | H8: =IFERROR(VLOOKUP(VLOOKUP(A8,'Sales Order'!A:C,3,FALSE),Employee!A:E,5,FALSE)&" "&VLOOKUP(VLOOKUP(A8,'Sales Order'!A:C,3,FALSE),Employee!A:C,3,FALSE)&" "&VLOOKUP(VLOOKUP(A8,'Sales Order'!A:C,3,FALSE),Employee!A:B,2,FALSE),"Not Specified") -> Mrs. Yael Peled | I8: =IFERROR(VLOOKUP(VLOOKUP(A8,'Sales Order'!A:C,3,FALSE),Employee!A:J,10,FALSE),"Not Specified") -> WA | J8: =VLOOKUP(B8,Product!A:B,2,FALSE) -> Product APITJ | K8: =VLOOKUP(VLOOKUP(B8,Product!A:D,4,FALSE),Category!A:B,2,FALSE) -> Produce | L8: =IFERROR(VLOOKUP(A8,'Sales Order'!A:D,4,FALSE),"") -> 38906 | M8: =IFERROR(VLOOKUP(A8,'Sales Order'!A:F,6,FALSE),"") -> 38910 | N8: =IFERROR(VLOOKUP(VLOOKUP(A8,'Sales Order'!A:G,7,FALSE),Shipper!A:B,2,FALSE),"Not Specified") -> Shipper ETYNR | O8: =IFERROR(VLOOKUP(A8,'Sales Order'!A:I,9,FALSE),"Not Specified") -> Destination SCQXA | P8: =IFERROR(VLOOKUP(A8,'Sales Order'!A:N,14,FALSE),"Not Specified") -> Brazil | Q8: =VLOOKUP(VLOOKUP(B8,Product!A:C,3,FALSE),Supplier!A:B,2,FALSE) -> Supplier JNNES | R8: =VLOOKUP(VLOOKUP(B8,Product!A:C,3,FALSE),Supplier!A:I,9,FALSE) -> Australia | S8: =IFERROR(IF(VLOOKUP(A8,'Sales Order'!A:H,8,FALSE)>100,"High Freight","Low Freight"),"Not Specified") -> Low Freight | T8: =C8*D8*(1-E8) -> 1261.4
A9: 10250 | B9: 65 | C9: 16.8 | D9: 15 | E9: 0.15 | F9: =IFERROR(VLOOKUP(VLOOKUP(A9,'Sales Order'!A:B,2,FALSE),Customer!A:C,3,FALSE),"Not Specified") -> Cohen, Shy | G9: =SUBSTITUTE(F9,",","",1) -> Cohen Shy | H9: =IFERROR(VLOOKUP(VLOOKUP(A9,'Sales Order'!A:C,3,FALSE),Employee!A:E,5,FALSE)&" "&VLOOKUP(VLOOKUP(A9,'Sales Order'!A:C,3,FALSE),Employee!A:C,3,FALSE)&" "&VLOOKUP(VLOOKUP(A9,'Sales Order'!A:C,3,FALSE),Employee!A:B,2,FALSE),"Not Specified") -> Mrs. Yael Peled | I9: =IFERROR(VLOOKUP(VLOOKUP(A9,'Sales Order'!A:C,3,FALSE),Employee!A:J,10,FALSE),"Not Specified") -> WA | J9: =VLOOKUP(B9,Product!A:B,2,FALSE) -> Product XYWBZ | K9: =VLOOKUP(VLOOKUP(B9,Product!A:D,4,FALSE),Category!A:B,2,FALSE) -> Condiments | L9: =IFERROR(VLOOKUP(A9,'Sales Order'!A:D,4,FALSE),"") -> 38906 | M9: =IFERROR(VLOOKUP(A9,'Sales Order'!A:F,6,FALSE),"") -> 38910 | N9: =IFERROR(VLOOKUP(VLOOKUP(A9,'Sales Order'!A:G,7,FALSE),Shipper!A:B,2,FALSE),"Not Specified") -> Shipper ETYNR | O9: =IFERROR(VLOOKUP(A9,'Sales Order'!A:I,9,FALSE),"Not Specified") -> Destination SCQXA | P9: =IFERROR(VLOOKUP(A9,'Sales Order'!A:N,14,FALSE),"Not Specified") -> Brazil | Q9: =VLOOKUP(VLOOKUP(B9,Product!A:C,3,FALSE),Supplier!A:B,2,FALSE) -> Supplier VHQZD | R9: =VLOOKUP(VLOOKUP(B9,Product!A:C,3,FALSE),Supplier!A:I,9,FALSE) -> USA | S9: =IFERROR(IF(VLOOKUP(A9,'Sales Order'!A:H,8,FALSE)>100,"High Freight","Low Freight"),"Not Specified") -> Low Freight | T9: =C9*D9*(1-E9) -> 214.2
A10: 10251 | B10: 22 | C10: 16.8 | D10: 6 | E10: 0.05 | F10: =IFERROR(VLOOKUP(VLOOKUP(A10,'Sales Order'!A:B,2,FALSE),Customer!A:C,3,FALSE),"Not Specified") -> Tuntisangaroon, Sittichai | G10: =SUBSTITUTE(F10,",","",1) -> Tuntisangaroon Sittichai | H10: =IFERROR(VLOOKUP(VLOOKUP(A10,'Sales Order'!A:C,3,FALSE),Employee!A:E,5,FALSE)&" "&VLOOKUP(VLOOKUP(A10,'Sales Order'!A:C,3,FALSE),Employee!A:C,3,FALSE)&" "&VLOOKUP(VLOOKUP(A10,'Sales Order'!A:C,3,FALSE),Employee!A:B,2,FALSE),"Not Specified") -> Ms. Judy Lew | I10: =IFERROR(VLOOKUP(VLOOKUP(A10,'Sales Order'!A:C,3,FALSE),Employee!A:J,10,FALSE),"Not Specified") -> WA | J10: =VLOOKUP(B10,Product!A:B,2,FALSE) -> Product CPHFY | K10: =VLOOKUP(VLOOKUP(B10,Product!A:D,4,FALSE),Category!A:B,2,FALSE) -> Grains/Cereals | L10: =IFERROR(VLOOKUP(A10,'Sales Order'!A:D,4,FALSE),"") -> 38906 | M10: =IFERROR(VLOOKUP(A10,'Sales Order'!A:F,6,FALSE),"") -> 38913 | N10: =IFERROR(VLOOKUP(VLOOKUP(A10,'Sales Order'!A:G,7,FALSE),Shipper!A:B,2,FALSE),"Not Specified") -> Shipper GVSUA | O10: =IFERROR(VLOOKUP(A10,'Sales Order'!A:I,9,FALSE),"Not Specified") -> Ship to 84-A | P10: =IFERROR(VLOOKUP(A10,'Sales Order'!A:N,14,FALSE),"Not Specified") -> France | Q10: =VLOOKUP(VLOOKUP(B10,Product!A:C,3,FALSE),Supplier!A:B,2,FALSE) -> Supplier QQYEU | R10: =VLOOKUP(VLOOKUP(B10,Product!A:C,3,FALSE),Supplier!A:I,9,FALSE) -> Sweden | S10: =IFERROR(IF(VLOOKUP(A10,'Sales Order'!A:H,8,FALSE)>100,"High Freight","Low Freight"),"Not Specified") -> Low Freight | T10: =C10*D10*(1-E10) -> 95.76
A11: 10251 | B11: 57 | C11: 15.6 | D11: 15 | E11: 0.05 | F11: =IFERROR(VLOOKUP(VLOOKUP(A11,'Sales Order'!A:B,2,FALSE),Customer!A:C,3,FALSE),"Not Specified") -> Tuntisangaroon, Sittichai | G11: =SUBSTITUTE(F11,",","",1) -> Tuntisangaroon Sittichai | H11: =IFERROR(VLOOKUP(VLOOKUP(A11,'Sales Order'!A:C,3,FALSE),Employee!A:E,5,FALSE)&" "&VLOOKUP(VLOOKUP(A11,'Sales Order'!A:C,3,FALSE),Employee!A:C,3,FALSE)&" "&VLOOKUP(VLOOKUP(A11,'Sales Order'!A:C,3,FALSE),Employee!A:B,2,FALSE),"Not Specified") -> Ms. Judy Lew | I11: =IFERROR(VLOOKUP(VLOOKUP(A11,'Sales Order'!A:C,3,FALSE),Employee!A:J,10,FALSE),"Not Specified") -> WA | J11: =VLOOKUP(B11,Product!A:B,2,FALSE) -> Product OVLQI | K11: =VLOOKUP(VLOOKUP(B11,Product!A:D,4,FALSE),Category!A:B,2,FALSE) -> Grains/Cereals | L11: =IFERROR(VLOOKUP(A11,'Sales Order'!A:D,4,FALSE),"") -> 38906 | M11: =IFERROR(VLOOKUP(A11,'Sales Order'!A:F,6,FALSE),"") -> 38913 | N11: =IFERROR(VLOOKUP(VLOOKUP(A11,'Sales Order'!A:G,7,FALSE),Shipper!A:B,2,FALSE),"Not Specified") -> Shipper GVSUA | O11: =IFERROR(VLOOKUP(A11,'Sales Order'!A:I,9,FALSE),"Not Specified") -> Ship to 84-A | P11: =IFERROR(VLOOKUP(A11,'Sales Order'!A:N,14,FALSE),"Not Specified") -> France | Q11: =VLOOKUP(VLOOKUP(B11,Product!A:C,3,FALSE),Supplier!A:B,2,FALSE) -> Supplier ZWZDM | R11: =VLOOKUP(VLOOKUP(B11,Product!A:C,3,FALSE),Supplier!A:I,9,FALSE) -> Italy | S11: =IFERROR(IF(VLOOKUP(A11,'Sales Order'!A:H,8,FALSE)>100,"High Freight","Low Freight"),"Not Specified") -> Low Freight | T11: =C11*D11*(1-E11) -> 222.3
A12: 10251 | B12: 65 | C12: 16.8 | D12: 20 | E12: 0 | F12: =IFERROR(VLOOKUP(VLOOKUP(A12,'Sales Order'!A:B,2,FALSE),Customer!A:C,3,FALSE),"Not Specified") -> Tuntisangaroon, Sittichai | G12: =SUBSTITUTE(F12,",","",1) -> Tuntisangaroon Sittichai | H12: =IFERROR(VLOOKUP(VLOOKUP(A12,'Sales Order'!A:C,3,FALSE),Employee!A:E,5,FALSE)&" "&VLOOKUP(VLOOKUP(A12,'Sales Order'!A:C,3,FALSE),Employee!A:C,3,FALSE)&" "&VLOOKUP(VLOOKUP(A12,'Sales Order'!A:C,3,FALSE),Employee!A:B,2,FALSE),"Not Specified") -> Ms. Judy Lew | I12: =IFERROR(VLOOKUP(VLOOKUP(A12,'Sales Order'!A:C,3,FALSE),Employee!A:J,10,FALSE),"Not Specified") -> WA | J12: =VLOOKUP(B12,Product!A:B,2,FALSE) -> Product XYWBZ | K12: =VLOOKUP(VLOOKUP(B12,Product!A:D,4,FALSE),Category!A:B,2,FALSE) -> Condiments | L12: =IFERROR(VLOOKUP(A12,'Sales Order'!A:D,4,FALSE),"") -> 38906 | M12: =IFERROR(VLOOKUP(A12,'Sales Order'!A:F,6,FALSE),"") -> 38913 | N12: =IFERROR(VLOOKUP(VLOOKUP(A12,'Sales Order'!A:G,7,FALSE),Shipper!A:B,2,FALSE),"Not Specified") -> Shipper GVSUA | O12: =IFERROR(VLOOKUP(A12,'Sales Order'!A:I,9,FALSE),"Not Specified") -> Ship to 84-A | P12: =IFERROR(VLOOKUP(A12,'Sales Order'!A:N,14,FALSE),"Not Specified") -> France | Q12: =VLOOKUP(VLOOKUP(B12,Product!A:C,3,FALSE),Supplier!A:B,2,FALSE) -> Supplier VHQZD | R12: =VLOOKUP(VLOOKUP(B12,Product!A:C,3,FALSE),Supplier!A:I,9,FALSE) -> USA | S12: =IFERROR(IF(VLOOKUP(A12,'Sales Order'!A:H,8,FALSE)>100,"High Freight","Low Freight"),"Not Specified") -> Low Freight | T12: =C12*D12*(1-E12) -> 336
A13: 10252 | B13: 20 | C13: 64.8 | D13: 40 | E13: 0.05 | F13: =IFERROR(VLOOKUP(VLOOKUP(A13,'Sales Order'!A:B,2,FALSE),Customer!A:C,3,FALSE),"Not Specified") -> Gulbis, Katrin | G13: =SUBSTITUTE(F13,",","",1) -> Gulbis Katrin | H13: =IFERROR(VLOOKUP(VLOOKUP(A13,'Sales Order'!A:C,3,FALSE),Employee!A:E,5,FALSE)&" "&VLOOKUP(VLOOKUP(A13,'Sales Order'!A:C,3,FALSE),Employee!A:C,3,FALSE)&" "&VLOOKUP(VLOOKUP(A13,'Sales Order'!A:C,3,FALSE),Employee!A:B,2,FALSE),"Not Specified") -> Mrs. Yael Peled | I13: =IFERROR(VLOOKUP(VLOOKUP(A13,'Sales Order'!A:C,3,FALSE),Employee!A:J,10,FALSE),"Not Specified") -> WA | J13: =VLOOKUP(B13,Product!A:B,2,FALSE) -> Product QHFFP | K13: =VLOOKUP(VLOOKUP(B13,Product!A:D,4,FALSE),Category!A:B,2,FALSE) -> Confections | L13: =IFERROR(VLOOKUP(A13,'Sales Order'!A:D,4,FALSE),"") -> 38907 | M13: =IFERROR(VLOOKUP(A13,'Sales Order'!A:F,6,FALSE),"") -> 38909 | N13: =IFERROR(VLOOKUP(VLOOKUP(A13,'Sales Order'!A:G,7,FALSE),Shipper!A:B,2,FALSE),"Not Specified") -> Shipper ETYNR | O13: =IFERROR(VLOOKUP(A13,'Sales Order'!A:I,9,FALSE),"Not Specified") -> Ship to 76-B | P13: =IFERROR(VLOOKUP(A13,'Sales Order'!A:N,14,FALSE),"Not Specified") -> Belgium | Q13: =VLOOKUP(VLOOKUP(B13,Product!A:C,3,FALSE),Supplier!A:B,2,FALSE) -> Supplier BWGYE | R13: =VLOOKUP(VLOOKUP(B13,Product!A:C,3,FALSE),Supplier!A:I,9,FALSE) -> UK | S13: =IFERROR(IF(VLOOKUP(A13,'Sales Order'!A:H,8,FALSE)>100,"High Freight","Low Freight"),"Not Specified") -> Low Freight | T13: =C13*D13*(1-E13) -> 2462.4
A14: 10252 | B14: 33 | C14: 2 | D14: 25 | E14: 0.05 | F14: =IFERROR(VLOOKUP(VLOOKUP(A14,'Sales Order'!A:B,2,FALSE),Customer!A:C,3,FALSE),"Not Specified") -> Gulbis, Katrin | G14: =SUBSTITUTE(F14,",","",1) -> Gulbis Katrin | H14: =IFERROR(VLOOKUP(VLOOKUP(A14,'Sales Order'!A:C,3,FALSE),Employee!A:E,5,FALSE)&" "&VLOOKUP(VLOOKUP(A14,'Sales Order'!A:C,3,FALSE),Employee!A:C,3,FALSE)&" "&VLOOKUP(VLOOKUP(A14,'Sales Order'!A:C,3,FALSE),Employee!A:B,2,FALSE),"Not Specified") -> Mrs. Yael Peled | I14: =IFERROR(VLOOKUP(VLOOKUP(A14,'Sales Order'!A:C,3,FALSE),Employee!A:J,10,FALSE),"Not Specified") -> WA | J14: =VLOOKUP(B14,Product!A:B,2,FALSE) -> Product ASTMN | K14: =VLOOKUP(VLOOKUP(B14,Product!A:D,4,FALSE),Category!A:B,2,FALSE) -> Dairy Product | L14: =IFERROR(VLOOKUP(A14,'Sales Order'!A:D,4,FALSE),"") -> 38907 | M14: =IFERROR(VLOOKUP(A14,'Sales Order'!A:F,6,FALSE),"") -> 38909 | N14: =IFERROR(VLOOKUP(VLOOKUP(A14,'Sales Order'!A:G,7,FALSE),Shipper!A:B,2,FALSE),"Not Specified") -> Shipper ETYNR | O14: =IFERROR(VLOOKUP(A14,'Sales Order'!A:I,9,FALSE),"Not Specified") -> Ship to 76-B | P14: =IFERROR(VLOOKUP(A14,'Sales Order'!A:N,14,FALSE),"Not Specified") -> Belgium | Q14: =VLOOKUP(VLOOKUP(B14,Product!A:C,3,FALSE),Supplier!A:B,2,FALSE) -> Supplier NZLIF | R14: =VLOOKUP(VLOOKUP(B14,Product!A:C,3,FALSE),Supplier!A:I,9,FALSE) -> Norway | S14: =IFERROR(IF(VLOOKUP(A14,'Sales Order'!A:H,8,FALSE)>100,"High Freight","Low Freight"),"Not Specified") -> Low Freight | T14: =C14*D14*(1-E14) -> 47.5
A15: 10252 | B15: 60 | C15: 27.2 | D15: 40 | E15: 0 | F15: =IFERROR(VLOOKUP(VLOOKUP(A15,'Sales Order'!A:B,2,FALSE),Customer!A:C,3,FALSE),"Not Specified") -> Gulbis, Katrin | G15: =SUBSTITUTE(F15,",","",1) -> Gulbis Katrin | H15: =IFERROR(VLOOKUP(VLOOKUP(A15,'Sales Order'!A:C,3,FALSE),Employee!A:E,5,FALSE)&" "&VLOOKUP(VLOOKUP(A15,'Sales Order'!A:C,3,FALSE),Employee!A:C,3,FALSE)&" "&VLOOKUP(VLOOKUP(A15,'Sales Order'!A:C,3,FALSE),Employee!A:B,2,FALSE),"Not Specified") -> Mrs. Yael Peled | I15: =IFERROR(VLOOKUP(VLOOKUP(A15,'Sales Order'!A:C,3,FALSE),Employee!A:J,10,FALSE),"Not Specified") -> WA | J15: =VLOOKUP(B15,Product!A:B,2,FALSE) -> Product WHBYK | K15: =VLOOKUP(VLOOKUP(B15,Product!A:D,4,FALSE),Category!A:B,2,FALSE) -> Dairy Product | L15: =IFERROR(VLOOKUP(A15,'Sales Order'!A:D,4,FALSE),"") -> 38907 | M15: =IFERROR(VLOOKUP(A15,'Sales Order'!A:F,6,FALSE),"") -> 38909 | N15: =IFERROR(VLOOKUP(VLOOKUP(A15,'Sales Order'!A:G,7,FALSE),Shipper!A:B,2,FALSE),"Not Specified") -> Shipper ETYNR | O15: =IFERROR(VLOOKUP(A15,'Sales Order'!A:I,9,FALSE),"Not Specified") -> Ship to 76-B | P15: =IFERROR(VLOOKUP(A15,'Sales Order'!A:N,14,FALSE),"Not Specified") -> Belgium | Q15: =VLOOKUP(VLOOKUP(B15,Product!A:C,3,FALSE),Supplier!A:B,2,FALSE) -> Supplier OAVQT | R15: =VLOOKUP(VLOOKUP(B15,Product!A:C,3,FALSE),Supplier!A:I,9,FALSE) -> France | S15: =IFERROR(IF(VLOOKUP(A15,'Sales Order'!A:H,8,FALSE)>100,"High Freight","Low Freight"),"Not Specified") -> Low Freight | T15: =C15*D15*(1-E15) -> 1088
A16: 10253 | B16: 31 | C16: 10 | D16: 20 | E16: 0 | F16: =IFERROR(VLOOKUP(VLOOKUP(A16,'Sales Order'!A:B,2,FALSE),Customer!A:C,3,FALSE),"Not Specified") -> Cohen, Shy | G16: =SUBSTITUTE(F16,",","",1) -> Cohen Shy | H16: =IFERROR(VLOOKUP(VLOOKUP(A16,'Sales Order'!A:C,3,FALSE),Employee!A:E,5,FALSE)&" "&VLOOKUP(VLOOKUP(A16,'Sales Order'!A:C,3,FALSE),Employee!A:C,3,FALSE)&" "&VLOOKUP(VLOOKUP(A16,'Sales Order'!A:C,3,FALSE),Employee!A:B,2,FALSE),"Not Specified") -> Ms. Judy Lew | I16: =IFERROR(VLOOKUP(VLOOKUP(A16,'Sales Order'!A:C,3,FALSE),Employee!A:J,10,FALSE),"Not Specified") -> WA | J16: =VLOOKUP(B16,Product!A:B,2,FALSE) -> Product XWOXC | K16: =VLOOKUP(VLOOKUP(B16,Product!A:D,4,FALSE),Category!A:B,2,FALSE) -> Dairy Product | L16: =IFERROR(VLOOKUP(A16,'Sales Order'!A:D,4,FALSE),"") -> 38908 | M16: =IFERROR(VLOOKUP(A16,'Sales Order'!A:F,6,FALSE),"") -> 38914 | N16: =IFERROR(VLOOKUP(VLOOKUP(A16,'Sales Order'!A:G,7,FALSE),Shipper!A:B,2,FALSE),"Not Specified") -> Shipper ETYNR | O16: =IFERROR(VLOOKUP(A16,'Sales Order'!A:I,9,FALSE),"Not Specified") -> Destination JPAIY | P16: =IFERROR(VLOOKUP(A16,'Sales Order'!A:N,14,FALSE),"Not Specified") -> Brazil | Q16: =VLOOKUP(VLOOKUP(B16,Product!A:C,3,FALSE),Supplier!A:B,2,FALSE) -> Supplier KEREV | R16: =VLOOKUP(VLOOKUP(B16,Product!A:C,3,FALSE),Supplier!A:I,9,FALSE) -> Italy | S16: =IFERROR(IF(VLOOKUP(A16,'Sales Order'!A:H,8,FALSE)>100,"High Freight","Low Freight"),"Not Specified") -> Low Freight | T16: =C16*D16*(1-E16) -> 200
A17: 10253 | B17: 39 | C17: 14.4 | D17: 42 | E17: 0 | F17: =IFERROR(VLOOKUP(VLOOKUP(A17,'Sales Order'!A:B,2,FALSE),Customer!A:C,3,FALSE),"Not Specified") -> Cohen, Shy | G17: =SUBSTITUTE(F17,",","",1) -> Cohen Shy | H17: =IFERROR(VLOOKUP(VLOOKUP(A17,'Sales Order'!A:C,3,FALSE),Employee!A:E,5,FALSE)&" "&VLOOKUP(VLOOKUP(A17,'Sales Order'!A:C,3,FALSE),Employee!A:C,3,FALSE)&" "&VLOOKUP(VLOOKUP(A17,'Sales Order'!A:C,3,FALSE),Employee!A:B,2,FALSE),"Not Specified") -> Ms. Judy Lew | I17: =IFERROR(VLOOKUP(VLOOKUP(A17,'Sales Order'!A:C,3,FALSE),Employee!A:J,10,FALSE),"Not Specified") -> WA | J17: =VLOOKUP(B17,Product!A:B,2,FALSE) -> Product LSOFL | K17: =VLOOKUP(VLOOKUP(B17,Product!A:D,4,FALSE),Category!A:B,2,FALSE) -> Beverages | L17: =IFERROR(VLOOKUP(A17,'Sales Order'!A:D,4,FALSE),"") -> 38908 | M17: =IFERROR(VLOOKUP(A17,'Sales Order'!A:F,6,FALSE),"") -> 38914 | N17: =IFERROR(VLOOKUP(VLOOKUP(A17,'Sales Order'!A:G,7,FALSE),Shipper!A:B,2,FALSE),"Not Specified") -> Shipper ETYNR | O17: =IFERROR(VLOOKUP(A17,'Sales Order'!A:I,9,FALSE),"Not Specified") -> Destination JPAIY | P17: =IFERROR(VLOOKUP(A17,'Sales Order'!A:N,14,FALSE),"Not Specified") -> Brazil | Q17: =VLOOKUP(VLOOKUP(B17,Product!A:C,3,FALSE),Supplier!A:B,2,FALSE) -> Supplier LVJUA | R17: =VLOOKUP(VLOOKUP(B17,Product!A:C,3,FALSE),Supplier!A:I,9,FALSE) -> France | S17: =IFERROR(IF(VLOOKUP(A17,'Sales Order'!A:H,8,FALSE)>100,"High Freight","Low Freight"),"Not Specified") -> Low Freight | T17: =C17*D17*(1-E17) -> 604.8
A18: 10253 | B18: 49 | C18: 16 | D18: 40 | E18: 0 | F18: =IFERROR(VLOOKUP(VLOOKUP(A18,'Sales Order'!A:B,2,FALSE),Customer!A:C,3,FALSE),"Not Specified") -> Cohen, Shy | G18: =SUBSTITUTE(F18,",","",1) -> Cohen Shy | H18: =IFERROR(VLOOKUP(VLOOKUP(A18,'Sales Order'!A:C,3,FALSE),Employee!A:E,5,FALSE)&" "&VLOOKUP(VLOOKUP(A18,'Sales Order'!A:C,3,FALSE),Employee!A:C,3,FALSE)&" "&VLOOKUP(VLOOKUP(A18,'Sales Order'!A:C,3,FALSE),Employee!A:B,2,FALSE),"Not Specified") -> Ms. Judy Lew | I18: =IFERROR(VLOOKUP(VLOOKUP(A18,'Sales Order'!A:C,3,FALSE),Employee!A:J,10,FALSE),"Not Specified") -> WA | J18: =VLOOKUP(B18,Product!A:B,2,FALSE) -> Product FPYPN | K18: =VLOOKUP(VLOOKUP(B18,Product!A:D,4,FALSE),Category!A:B,2,FALSE) -> Confections | L18: =IFERROR(VLOOKUP(A18,'Sales Order'!A:D,4,FALSE),"") -> 38908 | M18: =IFERROR(VLOOKUP(A18,'Sales Order'!A:F,6,FALSE),"") -> 38914 | N18: =IFERROR(VLOOKUP(VLOOKUP(A18,'Sales Order'!A:G,7,FALSE),Shipper!A:B,2,FALSE),"Not Specified") -> Shipper ETYNR | O18: =IFERROR(VLOOKUP(A18,'Sales Order'!A:I,9,FALSE),"Not Specified") -> Destination JPAIY | P18: =IFERROR(VLOOKUP(A18,'Sales Order'!A:N,14,FALSE),"Not Specified") -> Brazil | Q18: =VLOOKUP(VLOOKUP(B18,Product!A:C,3,FALSE),Supplier!A:B,2,FALSE) -> Supplier ELCRN | R18: =VLOOKUP(VLOOKUP(B18,Product!A:C,3,FALSE),Supplier!A:I,9,FALSE) -> Finland | S18: =IFERROR(IF(VLOOKUP(A18,'Sales Order'!A:H,8,FALSE)>100,"High Freight","Low Freight"),"Not Specified") -> Low Freight | T18: =C18*D18*(1-E18) -> 640
... A2156: 11077 | B2156: 77 | C2156: 13 | D2156: 2 | E2156: 0 | F2156: =IFERROR(VLOOKUP(VLOOKUP(A2156,'Sales Order'!A:B,2,FALSE),Customer!A:C,3,FALSE),"Not Specified") -> Moore, Michael | G2156: =SUBSTITUTE(F2156,",","",1) -> Moore Michael | H2156: =IFERROR(VLOOKUP(VLOOKUP(A2156,'Sales Order'!A:C,3,FALSE),Employee!A:E,5,FALSE)&" "&VLOOKUP(VLOOKUP(A2156,'Sales Order'!A:C,3,FALSE),Employee!A:C,3,FALSE)&" "&VLOOKUP(VLOOKUP(A2156,'Sales Order'!A:C,3,FALSE),Employee!A:B,2,FALSE),"Not Specified") -> Ms. Sara Davis | I2156: =IFERROR(VLOOKUP(VLOOKUP(A2156,'Sales Order'!A:C,3,FALSE),Employee!A:J,10,FALSE),"Not Specified") -> WA | J2156: =VLOOKUP(B2156,Product!A:B,2,FALSE) -> Product LUNZZ | K2156: =VLOOKUP(VLOOKUP(B2156,Product!A:D,4,FALSE),Category!A:B,2,FALSE) -> Condiments | L2156: =IFERROR(VLOOKUP(A2156,'Sales Order'!A:D,4,FALSE),"") -> 39574 | M2156: =IFERROR(VLOOKUP(A2156,'Sales Order'!A:F,6,FALSE),"") -> 0 | N2156: =IFERROR(VLOOKUP(VLOOKUP(A2156,'Sales Order'!A:G,7,FALSE),Shipper!A:B,2,FALSE),"Not Specified") -> Shipper ETYNR | O2156: =IFERROR(VLOOKUP(A2156,'Sales Order'!A:I,9,FALSE),"Not Specified") -> Ship to 65-A | P2156: =IFERROR(VLOOKUP(A2156,'Sales Order'!A:N,14,FALSE),"Not Specified") -> USA | Q2156: =VLOOKUP(VLOOKUP(B2156,Product!A:C,3,FALSE),Supplier!A:B,2,FALSE) -> Supplier SVIYA | R2156: =VLOOKUP(VLOOKUP(B2156,Product!A:C,3,FALSE),Supplier!A:I,9,FALSE) -> Germany | S2156: =IFERROR(IF(VLOOKUP(A2156,'Sales Order'!A:H,8,FALSE)>100,"High Freight","Low Freight"),"Not Specified") -> Low Freight | T2156: =C2156*D2156*(1-E2156) -> 26

Sheet Pivot_Table
A1: Row Labels | B1: Sum of Revenue | E1: Row Labels | F1: Sum of Revenue
A2: Beverages | B2: 267868.18 | E2: 2006 | F2: 205780.57
A3: Condiments | B3: 106047.09 | E3: 2007 | F3: 617085.2
A4: Confections | B4: 167357.22 | E4: 2008 | F4: 440623.87
A5: Dairy Product | B5: 234507.29 | E5: <7/8/2006 | F5: 2303.4
A6: Grains/Cereals | B6: 95744.588 | E6: (blank) | F6: 2303.4
A7: Meat/Poultry | B7: 163022.36 | E7: Grand Total | F7: 1265793
A8: Produce | B8: 99984.58
A9: Seafood | B9: 131261.74
A10: Grand Total | B10: 1265793
A11: REVENUE BY PRODUCT CATEGORY
A13: Row Labels | B13: Sum of Revenue
A14: Dr. Don Funk | B14: 166537.76
A15: Mr. Paul Suurs | B15: 72049.73
A16: Mr. Russell King | B16: 124568.24
A17: Mr. Sven Buck | B17: 68352.283
A18: Mrs. Yael Peled | B18: 232890.85
A19: Ms. Judy Lew | B19: 202812.84
A20: Ms. Maria Cameron | B20: 126862.28
A21: Ms. Sara Davis | B21: 192107.6
A22: Ms. Zoya Dolgopyatova | B22: 77308.067
A23: Not Specified | B23: 2303.4
A24: Grand Total | B24: 1265793
A25: REVENUE BY EMPLOYEE
A29: Row Labels | B29: Sum of Revenue
A30: Argentina | B30: 8119.1
A31: Austria | B31: 128003.84
A32: Belgium | B32: 33824.855
A33: Brazil | B33: 106925.78
A34: Canada | B34: 50196.29
A35: Denmark | B35: 32661.023
A36: Finland | B36: 18810.052
A37: France | B37: 80918.322
A38: Germany | B38: 228421.23
A39: Ireland | B39: 49979.905
A40: Italy | B40: 15770.155
A41: Mexico | B41: 23582.078
... A52: Grand Total | B52: 1265793
A53: REVENUE BY COUNTRY
A56: Row Labels | B56: Sum of Revenue
A57: Shipper ETYNR | B57: 533547.63
A58: Shipper GVSUA | B58: 346976.54
A59: Shipper ZHISN | B59: 382965.47
A60: Not Specified | B60: 2303.4
A61: Grand Total | B61: 1265793
A62: SHIPPER REVENUE
A65: Row Labels | B65: Count of orderid
A66: High Freight | B66: 620
A67: Low Freight | B67: 1530
A68: Not Specified | B68: 5
A69: Grand Total | B69: 2155
A70: FREIGHT ANALYSIS

Sheet Assessment Brief
A1: Assessment Instructions Using these tables as references, do the following: 1. Populate all columns in the "Order Detail" sheet. This can be done largely with any lookUp function of your choice from other tables in this workbook. a. For Employee Name Column, if an employee's first name, last name, and title are John, Doe, and Mr. respectively. What is expected in the Employee Full Nam Column is Mr. John Doe b. For Freight Category column, if freight for order is greater than 100 return 'High Freight' else 'Low Freight'. c. Revenue can be calculated using the price and quantity ordered columns. 2. Create pivot table and charts from the fully populated sheet and generate these insights. a. Revenue generated by product category b. Top 10 Employees by revenue generated c. Revenue Trend d. Include other visuals 3. Create a dashboard to show all pivot charts in one locations. See sample dashboard below 4. Include slicers and timelines to make your report interactive. 5. In a detailed powerpoint presentation, summarize your findings from analyzing the data. Things to capture in the presentation are: -- Descriptive Analytics showing details about what has happened. -- Possible Root Cause Analysis explaining why key things happened -- Recommedations to improve the business in areas that are poor in performance. Note: The key metrics are Revenue, Profit, Transaction Count

Sheet Sales Order
A1: orderid | B1: custid | C1: empid | D1: orderdate | E1: requireddate | F1: shippeddate | G1: shipperid | H1: freight | I1: shipname | J1: shipaddress | K1: shipcity | L1: shipregion | M1: shippostalcode | N1: shipcountry | O1: chargeid
A2: 10250 | B2: 34 | C2: 4 | D2: 38906 | E2: 38934 | F2: 38910 | G2: 2 | H2: 65.83 | I2: Destination SCQXA | J2: Rua do Paço, 7890 | K2: Rio de Janeiro | L2: RJ | M2: 10195 | N2: Brazil | O2: {ch_743w32_TEST}
A3: 10251 | B3: 84 | C3: 3 | D3: 38906 | E3: 38934 | F3: 38913 | G3: 1 | H3: 41.34 | I3: Ship to 84-A | J3: 3456, rue du Commerce | K3: Lyon | M3: 10342 | N3: France | O3: {ch_743w32_TEST}
A4: 10252 | B4: 76 | C4: 4 | D4: 38907 | E4: 38935 | F4: 38909 | G4: 2 | H4: 51.3 | I4: Ship to 76-B | J4: Boulevard Tirou, 9012 | K4: Charleroi | M4: 10318 | N4: Belgium | O4: {ch_743w32_TEST}
A5: 10253 | B5: 34 | C5: 3 | D5: 38908 | E5: 38922 | F5: 38914 | G5: 2 | H5: 58.17 | I5: Destination JPAIY | J5: Rua do Paço, 8901 | K5: Rio de Janeiro | L5: RJ | M5: 10196 | N5: Brazil | O5: {ch_743w32_TEST}
A6: 10254 | B6: 14 | C6: 5 | D6: 38909 | E6: 38937 | F6: 38921 | G6: 2 | H6: 22.98 | I6: Destination YUJRD | J6: Hauptstr. 1234 | K6: Bern | M6: 10139 | N6: Switzerland | O6: {ch_743w32_TEST}
A7: 10255 | B7: 68 | C7: 9 | D7: 38910 | E7: 38938 | F7: 38913 | G7: 3 | H7: 148.33 | I7: Ship to 68-A | J7: Starenweg 6789 | K7: Genève | M7: 10294 | N7: Switzerland | O7: {ch_743w32_TEST}
A8: 10256 | B8: 88 | C8: 3 | D8: 38913 | E8: 38941 | F8: 38915 | G8: 2 | H8: 13.97 | I8: Ship to 88-B | J8: Rua do Mercado, 5678 | K8: Resende | L8: SP | M8: 10354 | N8: Brazil | O8: {ch_743w32_TEST}
A9: 10257 | B9: 35 | C9: 4 | D9: 38914 | E9: 38942 | F9: 38920 | G9: 3 | H9: 81.91 | I9: Destination JYDLM | J9: Carrera1234 con Ave. Carlos Soublette #8-35 | K9: San Cristóbal | L9: Táchira | M9: 10199 | N9: Venezuela | O9: {ch_743w32_TEST}
A10: 10258 | B10: 20 | C10: 1 | D10: 38915 | E10: 38943 | F10: 38921 | G10: 1 | H10: 140.51 | I10: Destination RVDMF | J10: Kirchgasse 9012 | K10: Graz | M10: 10157 | N10: Austria | O10: {ch_743w32_TEST}
A11: 10259 | B11: 13 | C11: 4 | D11: 38916 | E11: 38944 | F11: 38923 | G11: 3 | H11: 3.25 | I11: Destination LGGCH | J11: Sierras de Granada 9012 | K11: México D.F. | M11: 10137 | N11: Mexico | O11: {ch_743w32_TEST}
A12: 10260 | B12: 56 | C12: 4 | D12: 38917 | E12: 38945 | F12: 38927 | G12: 1 | H12: 55.09 | I12: Ship to 56-A | J12: Mehrheimerstr. 0123 | K12: Köln | M12: 10258 | N12: Germany | O12: {ch_743w32_TEST}
A13: 10261 | B13: 61 | C13: 4 | D13: 38917 | E13: 38945 | F13: 38928 | G13: 2 | H13: 3.05 | I13: Ship to 61-B | J13: Rua da Panificadora, 6789 | K13: Rio de Janeiro | L13: RJ | M13: 10274 | N13: Brazil | O13: {ch_743w32_TEST}
A14: 10262 | B14: 65 | C14: 8 | D14: 38920 | E14: 38948 | F14: 38923 | G14: 3 | H14: 48.29 | I14: Ship to 65-B | J14: 8901 Milton Dr. | K14: Albuquerque | L14: NM | M14: 10286 | N14: USA | O14: {ch_743w32_TEST}
A15: 10263 | B15: 20 | C15: 9 | D15: 38921 | E15: 38949 | F15: 38929 | G15: 3 | H15: 146.06 | I15: Destination FFXKT | J15: Kirchgasse 0123 | K15: Graz | M15: 10158 | N15: Austria | O15: {ch_743w32_TEST}
A16: 10264 | B16: 24 | C16: 6 | D16: 38922 | E16: 38950 | F16: 38952 | G16: 3 | H16: 3.67 | I16: Destination KBSBN | J16: Åkergatan 9012 | K16: Bräcke | M16: 10167 | N16: Sweden | O16: {ch_743w32_TEST}
A17: 10265 | B17: 7 | C17: 2 | D17: 38923 | E17: 38951 | F17: 38941 | G17: 1 | H17: 55.28 | I17: Ship to 7-A | J17: 0123, place Kléber | K17: Strasbourg | M17: 10329 | N17: France | O17: {ch_743w32_TEST}
A18: 10266 | B18: 87 | C18: 3 | D18: 38924 | E18: 38966 | F18: 38929 | G18: 3 | H18: 25.73 | I18: Ship to 87-B | J18: Torikatu 2345 | K18: Oulu | M18: 10351 | N18: Finland | O18: {ch_743w32_TEST}
A19: 10267 | B19: 25 | C19: 4 | D19: 38927 | E19: 38955 | F19: 38935 | G19: 1 | H19: 208.58 | I19: Destination VAPXU | J19: Berliner Platz 0123 | K19: München | M19: 10168 | N19: Germany | O19: {ch_743w32_TEST}
A20: 10268 | B20: 33 | C20: 8 | D20: 38928 | E20: 38956 | F20: 38931 | G20: 3 | H20: 66.29 | I20: Destination QJVQH | J20: 5ª Ave. Los Palos Grandes 5678 | K20: Caracas | L20: DF | M20: 10193 | N20: Venezuela | O20: {ch_743w32_TEST}
A21: 10269 | B21: 89 | C21: 5 | D21: 38929 | E21: 38943 | F21: 38938 | G21: 1 | H21: 4.56 | I21: Ship to 89-B | J21: 8901 - 12th Ave. S. | K21: Seattle | L21: WA | M21: 10357 | N21: USA | O21: {ch_743w32_TEST}
A22: 10270 | B22: 87 | C22: 1 | D22: 38930 | E22: 38958 | F22: 38931 | G22: 1 | H22: 136.54 | I22: Ship to 87-B | J22: Torikatu 2345 | K22: Oulu | M22: 10351 | N22: Finland | O22: {ch_743w32_TEST}
A23: 10271 | B23: 75 | C23: 6 | D23: 38930 | E23: 38958 | F23: 38959 | G23: 2 | H23: 4.54 | I23: Ship to 75-C | J23: P.O. Box 7890 | K23: Lander | L23: WY | M23: 10316 | N23: USA | O23: {ch_743w32_TEST}
A24: 10272 | B24: 65 | C24: 6 | D24: 38931 | E24: 38959 | F24: 38935 | G24: 2 | H24: 98.03 | I24: Ship to 65-A | J24: 7890 Milton Dr. | K24: Albuquerque | L24: NM | M24: 10285 | N24: USA | O24: {ch_743w32_TEST}
A25: 10273 | B25: 63 | C25: 3 | D25: 38934 | E25: 38962 | F25: 38941 | G25: 3 | H25: 76.07 | I25: Ship to 63-A | J25: Taucherstraße 1234 | K25: Cunewalde | M25: 10279 | N25: Germany | O25: {ch_743w32_TEST}
A26: 10274 | B26: 85 | C26: 6 | D26: 38935 | E26: 38963 | F26: 38945 | G26: 1 | H26: 6.01 | I26: Ship to 85-B | J26: 6789 rue de l'Abbaye | K26: Reims | M26: 10345 | N26: France | O26: {ch_743w32_TEST}
A27: 10275 | B27: 49 | C27: 1 | D27: 38936 | E27: 38964 | F27: 38938 | G27: 1 | H27: 26.93 | I27: Ship to 49-A | J27: Via Ludovico il Moro 8901 | K27: Bergamo | M27: 10235 | N27: Italy | O27: {ch_743w32_TEST}
A28: 10276 | B28: 80 | C28: 8 | D28: 38937 | E28: 38951 | F28: 38943 | G28: 3 | H28: 13.84 | I28: Ship to 80-C | J28: Avda. Azteca 5678 | K28: México D.F. | M28: 10334 | N28: Mexico | O28: {ch_743w32_TEST}
A29: 10277 | B29: 52 | C29: 2 | D29: 38938 | E29: 38966 | F29: 38942 | G29: 3 | H29: 125.77 | I29: Ship to 52-A | J29: Heerstr. 9012 | K29: Leipzig | M29: 10247 | N29: Germany | O29: {ch_743w32_TEST}
A30: 10278 | B30: 5 | C30: 8 | D30: 38941 | E30: 38969 | F30: 38945 | G30: 2 | H30: 92.69 | I30: Ship to 5-C | J30: Berguvsvägen 1234 | K30: Luleå | M30: 10269 | N30: Sweden | O30: {ch_743w32_TEST}
A31: 10279 | B31: 44 | C31: 8 | D31: 38942 | E31: 38970 | F31: 38945 | G31: 2 | H31: 25.83 | I31: Ship to 44-A | J31: Magazinweg 4567 | K31: Frankfurt a.M. | M31: 10222 | N31: Germany | O31: {ch_743w32_TEST}
A32: 10280 | B32: 5 | C32: 2 | D32: 38943 | E32: 38971 | F32: 38972 | G32: 1 | H32: 8.98 | I32: Ship to 5-B | J32: Berguvsvägen 0123 | K32: Luleå | M32: 10268 | N32: Sweden | O32: {ch_743w32_TEST}
A33: 10281 | B33: 69 | C33: 4 | D33: 38943 | E33: 38957 | F33: 38950 | G33: 1 | H33: 2.94 | I33: Ship to 69-A | J33: Gran Vía, 9012 | K33: Madrid | M33: 10297 | N33: Spain | O33: {ch_743w32_TEST}
A34: 10282 | B34: 69 | C34: 4 | D34: 38944 | E34: 38972 | F34: 38950 | G34: 1 | H34: 12.69 | I34: Ship to 69-B | J34: Gran Vía, 0123 | K34: Madrid | M34: 10298 | N34: Spain | O34: {ch_743w32_TEST}
A35: 10283 | B35: 46 | C35: 3 | D35: 38945 | E35: 38973 | F35: 38952 | G35: 3 | H35: 84.81 | I35: Ship to 46-A | J35: Carrera 0123 con Ave. Bolívar #65-98 Llano Largo | K35: Barquisimeto | L35: Lara | M35: 10227 | N35: Venezuela | O35: {ch_743w32_TEST}
A36: 10284 | B36: 44 | C36: 4 | D36: 38948 | E36: 38976 | F36: 38956 | G36: 1 | H36: 76.56 | I36: Ship to 44-A | J36: Magazinweg 4567 | K36: Frankfurt a.M. | M36: 10222 | N36: Germany | O36: {ch_743w32_TEST}
A37: 10285 | B37: 63 | C37: 1 | D37: 38949 | E37: 38977 | F37: 38955 | G37: 2 | H37: 76.83 | I37: Ship to 63-B | J37: Taucherstraße 2345 | K37: Cunewalde | M37: 10280 | N37: Germany | O37: {ch_743w32_TEST}
A38: 10286 | B38: 63 | C38: 8 | D38: 38950 | E38: 38978 | F38: 38959 | G38: 3 | H38: 229.24 | I38: Ship to 63-B | J38: Taucherstraße 2345 | K38: Cunewalde | M38: 10280 | N38: Germany | O38: {ch_743w32_TEST}
A39: 10287 | B39: 67 | C39: 8 | D39: 38951 | E39: 38979 | F39: 38957 | G39: 3 | H39: 12.76 | I39: Ship to 67-A | J39: Av. Copacabana, 3456 | K39: Rio de Janeiro | L39: RJ | M39: 10291 | N39: Brazil | O39: {ch_743w32_TEST}
A40: 10288 | B40: 66 | C40: 4 | D40: 38952 | E40: 38980 | F40: 38963 | G40: 1 | H40: 7.45 | I40: Ship to 66-C | J40: Strada Provinciale 2345 | K40: Reggio Emilia | M40: 10290 | N40: Italy | O40: {ch_743w32_TEST}
A41: 10289 | B41: 11 | C41: 7 | D41: 38955 | E41: 38983 | F41: 38957 | G41: 3 | H41: 22.77 | I41: Destination DLEUN | J41: Fauntleroy Circus 4567 | K41: London | M41: 10132 | N41: UK | O41: {ch_743w32_TEST}
A42: 10290 | B42: 15 | C42: 8 | D42: 38956 | E42: 38984 | F42: 38963 | G42: 1 | H42: 79.7 | I42: Destination HQZHO | J42: Av. dos Lusíadas, 4567 | K42: Sao Paulo | L42: SP | M42: 10142 | N42: Brazil | O42: {ch_743w32_TEST}
A43: 10291 | B43: 61 | C43: 6 | D43: 38956 | E43: 38984 | F43: 38964 | G43: 2 | H43: 6.4 | I43: Ship to 61-A | J43: Rua da Panificadora, 5678 | K43: Rio de Janeiro | L43: RJ | M43: 10273 | N43: Brazil | O43: {ch_743w32_TEST}
A44: 10292 | B44: 81 | C44: 1 | D44: 38957 | E44: 38985 | F44: 38962 | G44: 2 | H44: 1.35 | I44: Ship to 81-A | J44: Av. Inês de Castro, 6789 | K44: Sao Paulo | L44: SP | M44: 10335 | N44: Brazil | O44: {ch_743w32_TEST}
A45: 10293 | B45: 80 | C45: 1 | D45: 38958 | E45: 38986 | F45: 38971 | G45: 3 | H45: 21.18 | I45: Ship to 80-B | J45: Avda. Azteca 4567 | K45: México D.F. | M45: 10333 | N45: Mexico | O45: {ch_743w32_TEST}
A46: 10294 | B46: 65 | C46: 4 | D46: 38959 | E46: 38987 | F46: 38965 | G46: 2 | H46: 147.26 | I46: Ship to 65-A | J46: 7890 Milton Dr. | K46: Albuquerque | L46: NM | M46: 10285 | N46: USA | O46: {ch_743w32_TEST}
A47: 10295 | B47: 85 | C47: 2 | D47: 38962 | E47: 38990 | F47: 38970 | G47: 2 | H47: 1.15 | I47: Ship to 85-C | J47: 7890 rue de l'Abbaye | K47: Reims | M47: 10346 | N47: France | O47: {ch_743w32_TEST}
A48: 10296 | B48: 46 | C48: 6 | D48: 38963 | E48: 38991 | F48: 38971 | G48: 1 | H48: 0.12 | I48: Ship to 46-C | J48: Carrera 2345 con Ave. Bolívar #65-98 Llano Largo | K48: Barquisimeto | L48: Lara | M48: 10229 | N48: Venezuela | O48: {ch_743w32_TEST}
A49: 10297 | B49: 7 | C49: 5 | D49: 38964 | E49: 39006 | F49: 38970 | G49: 2 | H49: 5.74 | I49: Ship to 7-C | J49: 2345, place Kléber | K49: Strasbourg | M49: 10331 | N49: France | O49: {ch_743w32_TEST}
A50: 10298 | B50: 37 | C50: 6 | D50: 38965 | E50: 38993 | F50: 38971 | G50: 2 | H50: 168.22 | I50: Destination ATSOA | J50: 4567 Johnstown Road | K50: Cork | L50: Co. Cork | M50: 10202 | N50: Ireland | O50: {ch_743w32_TEST}
A51: 10299 | B51: 67 | C51: 4 | D51: 38966 | E51: 38994 | F51: 38973 | G51: 2 | H51: 29.76 | I51: Ship to 67-A | J51: Av. Copacabana, 3456 | K51: Rio de Janeiro | L51: RJ | M51: 10291 | N51: Brazil | O51: {ch_743w32_TEST}
A52: 10300 | B52: 49 | C52: 2 | D52: 38969 | E52: 38997 | F52: 38978 | G52: 2 | H52: 17.68 | I52: Ship to 49-A | J52: Via Ludovico il Moro 8901 | K52: Bergamo | M52: 10235 | N52: Italy | O52: {ch_743w32_TEST}
A53: 10301 | B53: 86 | C53: 8 | D53: 38969 | E53: 38997 | F53: 38977 | G53: 2 | H53: 45.08 | I53: Ship to 86-A | J53: Adenauerallee 8901 | K53: Stuttgart | M53: 10347 | N53: Germany | O53: {ch_743w32_TEST}
A54: 10302 | B54: 76 | C54: 4 | D54: 38970 | E54: 38998 | F54: 38999 | G54: 2 | H54: 6.27 | I54: Ship to 76-B | J54: Boulevard Tirou, 9012 | K54: Charleroi | M54: 10318 | N54: Belgium | O54: {ch_743w32_TEST}
A55: 10303 | B55: 30 | C55: 7 | D55: 38971 | E55: 38999 | F55: 38978 | G55: 2 | H55: 107.83 | I55: Destination IIYDD | J55: C/ Romero, 5678 | K55: Sevilla | M55: 10183 | N55: Spain | O55: {ch_743w32_TEST}
A56: 10304 | B56: 80 | C56: 1 | D56: 38972 | E56: 39000 | F56: 38977 | G56: 2 | H56: 63.79 | I56: Ship to 80-C | J56: Avda. Azteca 5678 | K56: México D.F. | M56: 10334 | N56: Mexico | O56: {ch_743w32_TEST}
A57: 10305 | B57: 55 | C57: 8 | D57: 38973 | E57: 39001 | F57: 38999 | G57: 3 | H57: 257.62 | I57: Ship to 55-B | J57: 8901 Bering St. | K57: Anchorage | L57: AK | M57: 10256 | N57: USA | O57: {ch_743w32_TEST}
A58: 10306 | B58: 69 | C58: 1 | D58: 38976 | E58: 39004 | F58: 38983 | G58: 3 | H58: 7.56 | I58: Ship to 69-B | J58: Gran Vía, 0123 | K58: Madrid | M58: 10298 | N58: Spain | O58: {ch_743w32_TEST}
A59: 10307 | B59: 48 | C59: 2 | D59: 38977 | E59: 39005 | F59: 38985 | G59: 2 | H59: 0.56 | I59: Ship to 48-B | J59: 6789 Chiaroscuro Rd. | K59: Portland | L59: OR | M59: 10233 | N59: USA | O59: {ch_743w32_TEST}
A60: 10308 | B60: 2 | C60: 7 | D60: 38978 | E60: 39006 | F60: 38984 | G60: 3 | H60: 1.61 | I60: Destination QMVCI | J60: Avda. de la Constitución 2345 | K60: México D.F. | M60: 10180 | N60: Mexico | O60: {ch_743w32_TEST}
A61: 10309 | B61: 37 | C61: 3 | D61: 38979 | E61: 39007 | F61: 39013 | G61: 1 | H61: 47.3 | I61: Destination ATSOA | J61: 4567 Johnstown Road | K61: Cork | L61: Co. Cork | M61: 10202 | N61: Ireland | O61: {ch_743w32_TEST}
A62: 10310 | B62: 77 | C62: 8 | D62: 38980 | E62: 39008 | F62: 38987 | G62: 2 | H62: 17.52 | I62: Ship to 77-B | J62: 2345 Jefferson Way Suite 2 | K62: Portland | L62: OR | M62: 10321 | N62: USA | O62: {ch_743w32_TEST}
A63: 10311 | B63: 18 | C63: 1 | D63: 38980 | E63: 38994 | F63: 38986 | G63: 3 | H63: 24.69 | I63: Destination SNPXM | J63: 0123, rue des Cinquante Otages | K63: Nantes | M63: 10148 | N63: France | O63: {ch_743w32_TEST}
A64: 10312 | B64: 86 | C64: 2 | D64: 38983 | E64: 39011 | F64: 38993 | G64: 2 | H64: 40.26 | I64: Ship to 86-B | J64: Adenauerallee 9012 | K64: Stuttgart | M64: 10348 | N64: Germany | O64: {ch_743w32_TEST}
A65: 10313 | B65: 63 | C65: 2 | D65: 38984 | E65: 39012 | F65: 38994 | G65: 2 | H65: 1.96 | I65: Ship to 63-A | J65: Taucherstraße 1234 | K65: Cunewalde | M65: 10279 | N65: Germany | O65: {ch_743w32_TEST}
A66: 10314 | B66: 65 | C66: 1 | D66: 38985 | E66: 39013 | F66: 38994 | G66: 2 | H66: 74.16 | I66: Ship to 65-A | J66: 7890 Milton Dr. | K66: Albuquerque | L66: NM | M66: 10285 | N66: USA | O66: {ch_743w32_TEST}
A67: 10315 | B67: 38 | C67: 4 | D67: 38986 | E67: 39014 | F67: 38993 | G67: 2 | H67: 41.76 | I67: Destination AXVHD | J67: Garden House Crowther Way 9012 | K67: Cowes | L67: Isle of Wight | M67: 10207 | N67: UK | O67: {ch_743w32_TEST}
A68: 10316 | B68: 65 | C68: 1 | D68: 38987 | E68: 39015 | F68: 38998 | G68: 3 | H68: 150.15 | I68: Ship to 65-B | J68: 8901 Milton Dr. | K68: Albuquerque | L68: NM | M68: 10286 | N68: USA | O68: {ch_743w32_TEST}
A69: 10317 | B69: 48 | C69: 6 | D69: 38990 | E69: 39018 | F69: 39000 | G69: 1 | H69: 12.69 | I69: Ship to 48-B | J69: 6789 Chiaroscuro Rd. | K69: Portland | L69: OR | M69: 10233 | N69: USA | O69: {ch_743w32_TEST}
A70: 10318 | B70: 38 | C70: 8 | D70: 38991 | E70: 39019 | F70: 38994 | G70: 2 | H70: 4.73 | I70: Destination AXVHD | J70: Garden House Crowther Way 9012 | K70: Cowes | L70: Isle of Wight | M70: 10207 | N70: UK | O70: {ch_743w32_TEST}
A71: 10319 | B71: 80 | C71: 7 | D71: 38992 | E71: 39020 | F71: 39001 | G71: 3 | H71: 64.5 | I71: Ship to 80-B | J71: Avda. Azteca 4567 | K71: México D.F. | M71: 10333 | N71: Mexico | O71: {ch_743w32_TEST}
A72: 10320 | B72: 87 | C72: 5 | D72: 38993 | E72: 39007 | F72: 39008 | G72: 3 | H72: 34.57 | I72: Ship to 87-A | J72: Torikatu 1234 | K72: Oulu | M72: 10350 | N72: Finland | O72: {ch_743w32_TEST}
A73: 10321 | B73: 38 | C73: 3 | D73: 38993 | E73: 39021 | F73: 39001 | G73: 2 | H73: 3.43 | I73: Destination LMVGS | J73: Garden House Crowther Way 8901 | K73: Cowes | L73: Isle of Wight | M73: 10206 | N73: UK | O73: {ch_743w32_TEST}
A74: 10322 | B74: 58 | C74: 7 | D74: 38994 | E74: 39022 | F74: 39013 | G74: 3 | H74: 0.4 | I74: Ship to 58-A | J74: Calle Dr. Jorge Cash 3456 | K74: México D.F. | M74: 10261 | N74: Mexico | O74: {ch_743w32_TEST}
A75: 10323 | B75: 39 | C75: 4 | D75: 38997 | E75: 39025 | F75: 39004 | G75: 1 | H75: 4.88 | I75: Destination RMBHM | J75: Maubelstr. 1234 | K75: Brandenburg | M75: 10209 | N75: Germany | O75: {ch_743w32_TEST}
A76: 10324 | B76: 71 | C76: 9 | D76: 38998 | E76: 39026 | F76: 39000 | G76: 1 | H76: 214.27 | I76: Ship to 71-C | J76: 9012 Suffolk Ln. | K76: Boise | L76: ID | M76: 10307 | N76: USA | O76: {ch_743w32_TEST}
A77: 10325 | B77: 39 | C77: 1 | D77: 38999 | E77: 39013 | F77: 39004 | G77: 3 | H77: 64.86 | I77: Destination RMBHM | J77: Maubelstr. 1234 | K77: Brandenburg | M77: 10209 | N77: Germany | O77: {ch_743w32_TEST}
A78: 10326 | B78: 8 | C78: 4 | D78: 39000 | E78: 39028 | F78: 39004 | G78: 2 | H78: 77.92 | I78: Ship to 8-A | J78: C/ Araquil, 0123 | K78: Madrid | M78: 10359 | N78: Spain | O78: {ch_743w32_TEST}
A79: 10327 | B79: 24 | C79: 2 | D79: 39001 | E79: 39029 | F79: 39004 | G79: 1 | H79: 63.36 | I79: Destination NCKKO | J79: Åkergatan 7890 | K79: Bräcke | M79: 10165 | N79: Sweden | O79: {ch_743w32_TEST}
A80: 10328 | B80: 28 | C80: 4 | D80: 39004 | E80: 39032 | F80: 39007 | G80: 3 | H80: 87.03 | I80: Destination CIRQO | J80: Jardim das rosas n. 8901 | K80: Lisboa | M80: 10176 | N80: Portugal | O80: {ch_743w32_TEST}
A81: 10329 | B81: 75 | C81: 4 | D81: 39005 | E81: 39047 | F81: 39013 | G81: 2 | H81: 191.67 | I81: Ship to 75-C | J81: P.O. Box 7890 | K81: Lander | L81: WY | M81: 10316 | N81: USA | O81: {ch_743w32_TEST}
A82: 10330 | B82: 46 | C82: 3 | D82: 39006 | E82: 39034 | F82: 39018 | G82: 1 | H82: 12.75 | I82: Ship to 46-A | J82: Carrera 0123 con Ave. Bolívar #65-98 Llano Largo | K82: Barquisimeto | L82: Lara | M82: 10227 | N82: Venezuela | O82: {ch_743w32_TEST}
A83: 10331 | B83: 9 | C83: 9 | D83: 39006 | E83: 39048 | F83: 39011 | G83: 1 | H83: 10.19 | I83: Ship to 9-C | J83: 0123, rue des Bouchers | K83: Marseille | M83: 10369 | N83: France | O83: {ch_743w32_TEST}
A84: 10332 | B84: 51 | C84: 3 | D84: 39007 | E84: 39049 | F84: 39011 | G84: 2 | H84: 52.84 | I84: Ship to 51-B | J84: 7890 rue St. Laurent | K84: Montréal | L84: Québec | M84: 10245 | N84: Canada | O84: {ch_743w32_TEST}
A85: 10333 | B85: 87 | C85: 5 | D85: 39008 | E85: 39036 | F85: 39015 | G85: 3 | H85: 0.59 | I85: Ship to 87-C | J85: Torikatu 3456 | K85: Oulu | M85: 10352 | N85: Finland | O85: {ch_743w32_TEST}
A86: 10334 | B86: 84 | C86: 8 | D86: 39011 | E86: 39039 | F86: 39018 | G86: 2 | H86: 8.56 | I86: Ship to 84-B | J86: 4567, rue du Commerce | K86: Lyon | M86: 10343 | N86: France | O86: {ch_743w32_TEST}
A87: 10335 | B87: 37 | C87: 7 | D87: 39012 | E87: 39040 | F87: 39014 | G87: 2 | H87: 42.11 | I87: Destination ATSOA | J87: 4567 Johnstown Road | K87: Cork | L87: Co. Cork | M87: 10202 | N87: Ireland | O87: {ch_743w32_TEST}
A88: 10336 | B88: 60 | C88: 7 | D88: 39013 | E88: 39041 | F88: 39015 | G88: 2 | H88: 15.51 | I88: Ship to 60-B | J88: Estrada da saúde n. 3456 | K88: Lisboa | M88: 10271 | N88: Portugal | O88: {ch_743w32_TEST}
A89: 10337 | B89: 25 | C89: 4 | D89: 39014 | E89: 39042 | F89: 39019 | G89: 3 | H89: 108.26 | I89: Destination QOCBL | J89: Berliner Platz 1234 | K89: München | M89: 10169 | N89: Germany | O89: {ch_743w32_TEST}
A90: 10338 | B90: 55 | C90: 4 | D90: 39015 | E90: 39043 | F90: 39019 | G90: 3 | H90: 84.21 | I90: Ship to 55-C | J90: 9012 Bering St. | K90: Anchorage | L90: AK | M90: 10257 | N90: USA | O90: {ch_743w32_TEST}
A91: 10339 | B91: 51 | C91: 2 | D91: 39018 | E91: 39046 | F91: 39025 | G91: 2 | H91: 15.66 | I91: Ship to 51-C | J91: 8901 rue St. Laurent | K91: Montréal | L91: Québec | M91: 10246 | N91: Canada | O91: {ch_743w32_TEST}
A92: 10340 | B92: 9 | C92: 1 | D92: 39019 | E92: 39047 | F92: 39029 | G92: 3 | H92: 166.31 | I92: Ship to 9-A | J92: 8901, rue des Bouchers | K92: Marseille | M92: 10367 | N92: France | O92: {ch_743w32_TEST}
A93: 10341 | B93: 73 | C93: 7 | D93: 39019 | E93: 39047 | F93: 39026 | G93: 3 | H93: 26.78 | I93: Ship to 73-A | J93: Vinbæltet 1234 | K93: Kobenhavn | M93: 10310 | N93: Denmark | O93: {ch_743w32_TEST}
A94: 10342 | B94: 25 | C94: 4 | D94: 39020 | E94: 39034 | F94: 39025 | G94: 2 | H94: 54.83 | I94: Destination VAPXU | J94: Berliner Platz 0123 | K94: München | M94: 10168 | N94: Germany | O94: {ch_743w32_TEST}
A95: 10343 | B95: 44 | C95: 4 | D95: 39021 | E95: 39049 | F95: 39027 | G95: 1 | H95: 110.37 | I95: Ship to 44-A | J95: Magazinweg 4567 | K95: Frankfurt a.M. | M95: 10222 | N95: Germany | O95: {ch_743w32_TEST}
A96: 10344 | B96: 89 | C96: 4 | D96: 39022 | E96: 39050 | F96: 39026 | G96: 2 | H96: 23.29 | I96: Ship to 89-A | J96: 7890 - 12th Ave. S. | K96: Seattle | L96: WA | M96: 10356 | N96: USA | O96: {ch_743w32_TEST}
A97: 10345 | B97: 63 | C97: 2 | D97: 39025 | E97: 39053 | F97: 39032 | G97: 2 | H97: 249.06 | I97: Ship to 63-B | J97: Taucherstraße 2345 | K97: Cunewalde | M97: 10280 | N97: Germany | O97: {ch_743w32_TEST}
A98: 10346 | B98: 65 | C98: 3 | D98: 39026 | E98: 39068 | F98: 39029 | G98: 3 | H98: 142.08 | I98: Ship to 65-A | J98: 7890 Milton Dr. | K98: Albuquerque | L98: NM | M98: 10285 | N98: USA | O98: {ch_743w32_TEST}
A99: 10347 | B99: 21 | C99: 4 | D99: 39027 | E99: 39055 | F99: 39029 | G99: 3 | H99: 3.1 | I99: Destination KKELL | J99: Rua Orós, 4567 | K99: Sao Paulo | L99: SP | M99: 10162 | N99: Brazil | O99: {ch_743w32_TEST}
A100: 10348 | B100: 86 | C100: 4 | D100: 39028 | E100: 39056 | F100: 39036 | G100: 2 | H100: 0.78 | I100: Ship to 86-B | J100: Adenauerallee 9012 | K100: Stuttgart | M100: 10348 | N100: Germany | O100: {ch_743w32_TEST}
...

Sheet Category
A1: categoryid | B1: categoryname | C1: description | D1: picture
A2: 1 | B2: Beverages | C2: Soft drinks, coffees, teas, beers, and ales
A3: 2 | B3: Condiments | C3: Sweet and savory sauces, relishes, spreads, and seasonings
A4: 3 | B4: Confections | C4: Desserts, candies, and sweet breads
A5: 4 | B5: Dairy Product | C5: Cheeses
A6: 5 | B6: Grains/Cereals | C6: Breads, crackers, pasta, and cereal
A7: 6 | B7: Meat/Poultry | C7: Prepared meats
A8: 7 | B8: Produce | C8: Dried fruit and bean curd
A9: 8 | B9: Seafood | C9: Seaweed and fish

Sheet Customer
A1: custid | B1: companyname | C1: contactname | D1: contacttitle | E1: address | F1: city | G1: region | H1: postalcode | I1: country | J1: phone | K1: fax
A2: 1 | B2: Customer NRZBB | C2: Allen, Michael | D2: Sales Representative | E2: Obere Str. 0123 | F2: Berlin | H2: 10092 | I2: Germany | J2: 030-3456789 | K2: 030-0123456
A3: 2 | B3: Customer MLTDN | C3: Hassall, Mark | D3: Owner | E3: Avda. de la Constitución 5678 | F3: México D.F. | H3: 10077 | I3: Mexico | J3: (5) 789-0123 | K3: (5) 456-7890
A4: 3 | B4: Customer KBUDE | C4: Peoples, John | D4: Owner | E4: Mataderos 7890 | F4: México D.F. | H4: 10097 | I4: Mexico | J4: (5) 123-4567
A5: 4 | B5: Customer HFBZG | C5: Arndt, Torsten | D5: Sales Representative | E5: 7890 Hanover Sq. | F5: London | H5: 10046 | I5: UK | J5: (171) 456-7890 | K5: (171) 456-7891
A6: 5 | B6: Customer HGVLZ | C6: Higginbotham, Tom | D6: Order Administrator | E6: Berguvsvägen 5678 | F6: Luleå | H6: 10112 | I6: Sweden | J6: 0921-67 89 01 | K6: 0921-23 45 67
A7: 6 | B7: Customer XHXJV | C7: Poland, Carole | D7: Sales Representative | E7: Forsterstr. 7890 | F7: Mannheim | H7: 10117 | I7: Germany | J7: 0621-67890 | K7: 0621-12345
A8: 7 | B8: Customer QXVLA | C8: Bansal, Dushyant | D8: Marketing Manager | E8: 2345, place Kléber | F8: Strasbourg | H8: 10089 | I8: France | J8: 67.89.01.23 | K8: 67.89.01.24
A9: 8 | B9: Customer QUHWH | C9: Ilyina, Julia | D9: Owner | E9: C/ Araquil, 0123 | F9: Madrid | H9: 10104 | I9: Spain | J9: (91) 345 67 89 | K9: (91) 012 34 56
A10: 9 | B10: Customer RTXGC | C10: Raghav, Amritansh | D10: Owner | E10: 6789, rue des Bouchers | F10: Marseille | H10: 10105 | I10: France | J10: 23.45.67.89 | K10: 23.45.67.80
A11: 10 | B11: Customer EEALV | C11: Bassols, Pilar Colome | D11: Accounting Manager | E11: 8901 Tsawassen Blvd. | F11: Tsawassen | G11: BC | H11: 10111 | I11: Canada | J11: (604) 901-2345 | K11: (604) 678-9012
A12: 11 | B12: Customer UBHAU | C12: Jaffe, David | D12: Sales Representative | E12: Fauntleroy Circus 4567 | F12: London | H12: 10064 | I12: UK | J12: (171) 789-0123
A13: 12 | B13: Customer PSNMQ | C13: Ray, Mike | D13: Sales Agent | E13: Cerrito 3456 | F13: Buenos Aires | H13: 10057 | I13: Argentina | J13: (1) 890-1234 | K13: (1) 567-8901
A14: 13 | B14: Customer VMLOG | C14: Benito, Almudena | D14: Marketing Manager | E14: Sierras de Granada 7890 | F14: México D.F. | H14: 10056 | I14: Mexico | J14: (5) 456-7890 | K14: (5) 123-4567
A15: 14 | B15: Customer WNMAF | C15: Jelitto, Jacek | D15: Owner | E15: Hauptstr. 0123 | F15: Bern | H15: 10065 | I15: Switzerland | J15: 0452-678901
A16: 15 | B16: Customer JUWXK | C16: Richardson, Shawn | D16: Sales Associate | E16: Av. dos Lusíadas, 6789 | F16: Sao Paulo | G16: SP | H16: 10087 | I16: Brazil | J16: (11) 012-3456
A17: 16 | B17: Customer GYBBY | C17: Birkby, Dana | D17: Sales Representative | E17: Berkeley Gardens 0123 Brewery | F17: London | H17: 10039 | I17: UK | J17: (171) 234-5678 | K17: (171) 234-5679
A18: 17 | B18: Customer FEVNN | C18: Jones, TiAnna | D18: Order Administrator | E18: Walserweg 4567 | F18: Aachen | H18: 10067 | I18: Germany | J18: 0241-789012 | K18: 0241-345678
A19: 18 | B19: Customer BSVAR | C19: Rizaldy, Arif | D19: Owner | E19: 3456, rue des Cinquante Otages | F19: Nantes | H19: 10041 | I19: France | J19: 89.01.23.45 | K19: 89.01.23.46
A20: 19 | B20: Customer RFNQC | C20: Boseman, Randall | D20: Sales Agent | E20: 5678 King George | F20: London | H20: 10110 | I20: UK | J20: (171) 345-6789 | K20: (171) 345-6780
A21: 20 | B21: Customer THHDP | C21: Kane, John | D21: Sales Manager | E21: Kirchgasse 9012 | F21: Graz | H21: 10059 | I21: Austria | J21: 1234-5678 | K21: 9012-3456
A22: 21 | B22: Customer KIDPX | C22: Russo, Giuseppe | D22: Marketing Assistant | E22: Rua Orós, 3456 | F22: Sao Paulo | G22: SP | H22: 10096 | I22: Brazil | J22: (11) 456-7890
A23: 22 | B23: Customer DTDMN | C23: Bueno, Janaina Burdan, Neville | D23: Accounting Manager | E23: C/ Moralzarzal, 5678 | F23: Madrid | H23: 10080 | I23: Spain | J23: (91) 890 12 34 | K23: (91) 567 89 01
A24: 23 | B24: Customer WVFAF | C24: Khanna, Karan | D24: Assistant Sales Agent | E24: 4567, chaussée de Tournai | F24: Lille | H24: 10048 | I24: France | J24: 45.67.89.01 | K24: 45.67.89.02
A25: 24 | B25: Customer CYZTN | C25: San Juan, Patricia | D25: Owner | E25: Åkergatan 5678 | F25: Bräcke | H25: 10114 | I25: Sweden | J25: 0695-67 89 01
A26: 25 | B26: Customer AZJED | C26: Carlson, Jason | D26: Marketing Manager | E26: Berliner Platz 9012 | F26: München | H26: 10091 | I26: Germany | J26: 089-8901234 | K26: 089-5678901
A27: 26 | B27: Customer USDBG | C27: Koch, Paul | D27: Marketing Manager | E27: 9012, rue Royale | F27: Nantes | H27: 10101 | I27: France | J27: 34.56.78.90 | K27: 34.56.78.91
A28: 27 | B28: Customer WMFEA | C28: Schmöllerl, Martin | D28: Sales Representative | E28: Via Monte Bianco 4567 | F28: Torino | H28: 10099 | I28: Italy | J28: 011-2345678 | K28: 011-9012345
A29: 28 | B29: Customer XYUFB | C29: Cavaglieri, Giorgio | D29: Sales Manager | E29: Jardim das rosas n. 8901 | F29: Lisboa | H29: 10054 | I29: Portugal | J29: (1) 456-7890 | K29: (1) 123-4567
A30: 29 | B30: Customer MDLWA | C30: Kolesnikova, Katerina | D30: Marketing Manager | E30: Rambla de Cataluña, 8901 | F30: Barcelona | H30: 10081 | I30: Spain | J30: (93) 789 0123 | K30: (93) 456 7890
A31: 30 | B31: Customer KSLQF | C31: Shabalin, Rostislav | D31: Sales Manager | E31: C/ Romero, 1234 | F31: Sevilla | H31: 10075 | I31: Spain | J31: (95) 901 23 45
A32: 31 | B32: Customer YJCBX | C32: Cheng, Yao-Qiang | D32: Sales Associate | E32: Av. Brasil, 5678 | F32: Campinas | G32: SP | H32: 10128 | I32: Brazil | J32: (11) 567-8901
A33: 32 | B33: Customer YSIQX | C33: Krishnan, Venky | D33: Marketing Manager | E33: 6789 Baker Blvd. | F33: Eugene | G33: OR | H33: 10070 | I33: USA | J33: (503) 555-0122
A34: 33 | B34: Customer FVXPQ | C34: Sigurdarson, Hallur | D34: Owner | E34: 5ª Ave. Los Palos Grandes 3456 | F34: Caracas | G34: DF | H34: 10043 | I34: Venezuela | J34: (2) 789-0123 | K34: (2) 456-7890
A35: 34 | B35: Customer IBVRG | C35: Cohen, Shy | D35: Accounting Manager | E35: Rua do Paço, 7890 | F35: Rio de Janeiro | G35: RJ | H35: 10076 | I35: Brazil | J35: (21) 789-0123 | K35: (21) 789-0124
A36: 35 | B36: Customer UMTLM | C36: Langohr, Kris | D36: Sales Representative | E36: Carrera 1234 con Ave. Carlos Soublette #8-35 | F36: San Cristóbal | G36: Táchira | H36: 10066 | I36: Venezuela | J36: (5) 567-8901 | K36: (5) 234-5678
A37: 36 | B37: Customer LVJSO | C37: Smith, Denise | D37: Sales Representative | E37: City Center Plaza 2345 Main St. | F37: Elgin | G37: OR | H37: 10103 | I37: USA | J37: (503) 555-0126 | K37: (503) 555-0135
A38: 37 | B38: Customer FRXZL | C38: Crăciun, Ovidiu V. | D38: Sales Associate | E38: 9012 Johnstown Road | F38: Cork | G38: Co. Cork | H38: 10051 | I38: Ireland | J38: 8901 234 | K38: 5678 9012
A39: 38 | B39: Customer LJUCA | C39: Lee, Frank | D39: Marketing Manager | E39: Garden House Crowther Way 3456 | F39: Cowes | G39: Isle of Wight | H39: 10063 | I39: UK | J39: (198) 567-8901
A40: 39 | B40: Customer GLLAG | C40: Song, Lolan | D40: Sales Associate | E40: Maubelstr. 8901 | F40: Brandenburg | H40: 10060 | I40: Germany | J40: 0555-34567
A41: 40 | B41: Customer EFFTC | C41: De Oliveira, Jose | D41: Sales Representative | E41: 2345, avenue de l'Europe | F41: Versailles | H41: 10108 | I41: France | J41: 12.34.56.78 | K41: 12.34.56.79
A42: 41 | B42: Customer XIIWM | C42: Litton, Tim | D42: Sales Manager | E42: 3456 rue Alsace-Lorraine | F42: Toulouse | H42: 10053 | I42: France | J42: 90.12.34.56 | K42: 90.12.34.57
A43: 42 | B43: Customer IAIJK | C43: Steiner, Dominik | D43: Marketing Assistant | E43: 2345 Oak St. | F43: Vancouver | G43: BC | H43: 10098 | I43: Canada | J43: (604) 567-8901 | K43: (604) 234-5678
A44: 43 | B44: Customer UISOJ | C44: Deshpande, Anu | D44: Marketing Manager | E44: 8901 Orchestra Terrace | F44: Walla Walla | G44: WA | H44: 10069 | I44: USA | J44: (509) 555-0119 | K44: (509) 555-0130
A45: 44 | B45: Customer OXFRU | C45: Louverdis, George | D45: Sales Representative | E45: Magazinweg 8901 | F45: Frankfurt a.M. | H45: 10095 | I45: Germany | J45: 069-7890123 | K45: 069-4567890
A46: 45 | B46: Customer QXPPT | C46: Sunkammurali, Krishna | D46: Owner | E46: 1234 Polk St. Suite 5 | F46: San Francisco | G46: CA | H46: 10062 | I46: USA | J46: (415) 555-0118
A47: 46 | B47: Customer XPNIK | C47: Dressler, Marlies | D47: Accounting Manager | E47: Carrera 7890 con Ave. Bolívar #65-98 Llano Largo | F47: Barquisimeto | G47: Lara | H47: 10093 | I47: Venezuela | J47: (9) 789-0123 | K47: (9) 456-7890
A48: 47 | B48: Customer PSQUZ | C48: Lupu, Cornel | D48: Owner | E48: Ave. 5 de Mayo Porlamar 5678 | F48: I. de Margarita | G48: Nueva Esparta | H48: 10121 | I48: Venezuela | J48: (8) 01-23-45 | K48: (8) 67-89-01
A49: 48 | B49: Customer DVFMB | C49: Szymczak, Radosław | D49: Sales Manager | E49: 9012 Chiaroscuro Rd. | F49: Portland | G49: OR | H49: 10073 | I49: USA | J49: (503) 555-0117 | K49: (503) 555-0129
A50: 49 | B50: Customer CQRAA | C50: Duerr, Bernard | D50: Marketing Manager | E50: Via Ludovico il Moro 6789 | F50: Bergamo | H50: 10106 | I50: Italy | J50: 035-345678 | K50: 035-901234
A51: 50 | B51: Customer JYPSC | C51: Mace, Donald | D51: Sales Agent | E51: Rue Joseph-Bens 0123 | F51: Bruxelles | H51: 10074 | I51: Belgium | J51: (02) 890 12 34 | K51: (02) 567 89 01
A52: 51 | B52: Customer PVDZC | C52: Taylor, Maurice | D52: Marketing Assistant | E52: 8901 rue St. Laurent | F52: Montréal | G52: Québec | H52: 10040 | I52: Canada | J52: (514) 345-6789 | K52: (514) 012-3456
A53: 52 | B53: Customer PZNLA | C53: Dupont-Roc, Patrice | D53: Marketing Assistant | E53: Heerstr. 4567 | F53: Leipzig | H53: 10125 | I53: Germany | J53: 0342-12345
A54: 53 | B54: Customer GCJSG | C54: Mallit, Ken | D54: Sales Associate | E54: South House 1234 Queensbridge | F54: London | H54: 10061 | I54: UK | J54: (171) 890-1234 | K54: (171) 890-1235
A55: 54 | B55: Customer TDKEG | C55: Tiano, Mike | D55: Sales Agent | E55: Ing. Gustavo Moncada 0123 Piso 20-A | F55: Buenos Aires | H55: 10094 | I55: Argentina | J55: (1) 123-4567 | K55: (1) 890-1234
A56: 55 | B56: Customer KZQZT | C56: Egelund-Muller, Anja | D56: Sales Representative | E56: 7890 Bering St. | F56: Anchorage | G56: AK | H56: 10050 | I56: USA | J56: (907) 555-0115 | K56: (907) 555-0128
A57: 56 | B57: Customer QNIVZ | C57: Marinova, Nadejda | D57: Owner | E57: Mehrheimerstr. 9012 | F57: Köln | H57: 10047 | I57: Germany | J57: 0221-0123456 | K57: 0221-7890123
A58: 57 | B58: Customer WVAXS | C58: Tollevsen, Bjørn | D58: Owner | E58: 5678, boulevard Charonne | F58: Paris | H58: 10085 | I58: France | J58: (1) 89.01.23.45 | K58: (1) 89.01.23.46
A59: 58 | B59: Customer AHXHT | C59: Fakhouri, Fadi | D59: Sales Representative | E59: Calle Dr. Jorge Cash 8901 | F59: México D.F. | H59: 10116 | I59: Mexico | J59: (5) 890-1234 | K59: (5) 567-8901
A60: 59 | B60: Customer LOLJO | C60: Meston, Tosh | D60: Sales Manager | E60: Geislweg 2345 | F60: Salzburg | H60: 10127 | I60: Austria | J60: 4567-8901 | K60: 2345-6789
A61: 60 | B61: Customer QZURI | C61: Uppal, Sunil | D61: Sales Representative | E61: Estrada da saúde n. 6789 | F61: Lisboa | H61: 10083 | I61: Portugal | J61: (1) 789-0123
A62: 61 | B62: Customer WULWD | C62: Florczyk, Krzysztof | D62: Accounting Manager | E62: Rua da Panificadora, 1234 | F62: Rio de Janeiro | G62: RJ | H62: 10115 | I62: Brazil | J62: (21) 678-9012 | K62: (21) 678-9013
A63: 62 | B63: Customer WFIZJ | C63: Misiec, Anna | D63: Marketing Assistant | E63: Alameda dos Canàrios, 1234 | F63: Sao Paulo | G63: SP | H63: 10102 | I63: Brazil | J63: (11) 901-2345
A64: 63 | B64: Customer IRRVL | C64: Veronesi, Giorgio | D64: Accounting Manager | E64: Taucherstraße 1234 | F64: Cunewalde | H64: 10126 | I64: Germany | J64: 0372-12345
A65: 64 | B65: Customer LWGMD | C65: Gaffney, Lawrie | D65: Sales Representative | E65: Av. del Libertador 3456 | F65: Buenos Aires | H65: 10124 | I65: Argentina | J65: (1) 234-5678 | K65: (1) 901-2345
A66: 65 | B66: Customer NYUHS | C66: Moore, Michael | D66: Assistant Sales Representative | E66: 6789 Milton Dr. | F66: Albuquerque | G66: NM | H66: 10109 | I66: USA | J66: (505) 555-0125 | K66: (505) 555-0134
A67: 66 | B67: Customer LHANT | C67: Voss, Florian | D67: Sales Associate | E67: Strada Provinciale 7890 | F67: Reggio Emilia | H67: 10038 | I67: Italy | J67: 0522-012345 | K67: 0522-678901
A68: 67 | B68: Customer QVEPD | C68: Garden, Euan | D68: Assistant Sales Agent | E68: Av. Copacabana, 6789 | F68: Rio de Janeiro | G68: RJ | H68: 10052 | I68: Brazil | J68: (21) 345-6789
A69: 68 | B69: Customer CCKOT | C69: Myrcha, Jacek | D69: Sales Manager | E69: Grenzacherweg 0123 | F69: Genève | H69: 10122 | I69: Switzerland | J69: 0897-012345
A70: 69 | B70: Customer SIUIH | C70: Watters, Jason M. | D70: Accounting Manager | E70: Gran Vía, 4567 | F70: Madrid | H70: 10071 | I70: Spain | J70: (91) 567 8901 | K70: (91) 234 5678
A71: 70 | B71: Customer TMXGN | C71: Ginters, Kaspars | D71: Owner | E71: Erling Skakkes gate 2345 | F71: Stavern | H71: 10123 | I71: Norway | J71: 07-89 01 23 | K71: 07-45 67 89
A72: 71 | B72: Customer LCOUJ | C72: Navarro, Tomás | D72: Sales Representative | E72: 9012 Suffolk Ln. | F72: Boise | G72: ID | H72: 10078 | I72: USA | J72: (208) 555-0116
A73: 72 | B73: Customer AHPOP | C73: Welcker, Brian | D73: Sales Manager | E73: 4567 Wadhurst Rd. | F73: London | H73: 10088 | I73: UK | J73: (171) 901-2345 | K73: (171) 901-2346
A74: 73 | B74: Customer JMIKW | C74: Gonzalez, Nuria | D74: Owner | E74: Vinbæltet 3456 | F74: Kobenhavn | H74: 10079 | I74: Denmark | J74: 12 34 56 78 | K74: 90 12 34 56
A75: 74 | B75: Customer YSHXL | C75: O’Brien, Dave | D75: Marketing Manager | E75: 9012, rue Lauriston | F75: Paris | H75: 10058 | I75: France | J75: (1) 23.45.67.89 | K75: (1) 23.45.67.80
A76: 75 | B76: Customer XOJYP | C76: Wojciechowska, Agnieszka | D76: Sales Manager | E76: P.O. Box 1234 | F76: Lander | G76: WY | H76: 10113 | I76: USA | J76: (307) 555-0114 | K76: (307) 555-0127
A77: 76 | B77: Customer SFOGW | C77: Gulbis, Katrin | D77: Accounting Manager | E77: Boulevard Tirou, 2345 | F77: Charleroi | H77: 10100 | I77: Belgium | J77: (071) 56 78 90 12 | K77: (071) 34 56 78 90
A78: 77 | B78: Customer LCYBZ | C78: Osorio, Cristian | D78: Marketing Manager | E78: 2345 Jefferson Way Suite 2 | F78: Portland | G78: OR | H78: 10042 | I78: USA | J78: (503) 555-0120
A79: 78 | B79: Customer NLTYP | C79: Young, Robin | D79: Marketing Assistant | E79: 0123 Grizzly Peak Rd. | F79: Butte | G79: MT | H79: 10107 | I79: USA | J79: (406) 555-0121 | K79: (406) 555-0131
A80: 79 | B80: Customer FAPSM | C80: Wickham, Jim | D80: Marketing Manager | E80: Luisenstr. 0123 | F80: Münster | H80: 10118 | I80: Germany | J80: 0251-456789 | K80: 0251-012345
A81: 80 | B81: Customer VONTK | C81: Geschwandtner, Jens | D81: Owner | E81: Avda. Azteca 4567 | F81: México D.F. | H81: 10044 | I81: Mexico | J81: (5) 678-9012
A82: 81 | B82: Customer YQQWW | C82: Nagel, Jean-Philippe | D82: Sales Representative | E82: Av. Inês de Castro, 1234 | F82: Sao Paulo | G82: SP | H82: 10120 | I82: Brazil | J82: (11) 123-4567 | K82: (11) 234-5678
A83: 82 | B83: Customer EYHKM | C83: Veninga, Tjeerd | D83: Sales Associate | E83: 1234 DaVinci Blvd. | F83: Kirkland | G83: WA | H83: 10119 | I83: USA | J83: (206) 555-0124 | K83: (206) 555-0133
A84: 83 | B84: Customer ZRNDE | C84: Fonteneau, Karl | D84: Sales Manager | E84: Smagsloget 3456 | F84: Århus | H84: 10090 | I84: Denmark | J84: 23 45 67 89 | K84: 01 23 45 67
A85: 84 | B85: Customer NRCSK | C85: Tuntisangaroon, Sittichai | D85: Sales Agent | E85: 6789, rue du Commerce | F85: Lyon | H85: 10072 | I85: France | J85: 78.90.12.34 | K85: 78.90.12.35
A86: 85 | B86: Customer ENQZT | C86: McLin, Nkenge | D86: Accounting Manager | E86: 5678 rue de l'Abbaye | F86: Reims | H86: 10082 | I86: France | J86: 56.78.90.12 | K86: 56.78.90.13
A87: 86 | B87: Customer SNXOJ | C87: Syamala, Manoj | D87: Sales Representative | E87: Adenauerallee 7890 | F87: Stuttgart | H87: 10086 | I87: Germany | J87: 0711-345678 | K87: 0711-901234
A88: 87 | B88: Customer ZHYOS | C88: Ludwig, Michael | D88: Accounting Manager | E88: Torikatu 9012 | F88: Oulu | H88: 10045 | I88: Finland | J88: 981-123456 | K88: 981-789012
A89: 88 | B89: Customer SRQVM | C89: Li, Yan | D89: Sales Manager | E89: Rua do Mercado, 4567 | F89: Resende | G89: SP | H89: 10084 | I89: Brazil | J89: (14) 234-5678
A90: 89 | B90: Customer YBQTI | C90: Smith Jr., Ronaldo | D90: Owner | E90: 8901 - 14th Ave. S. Suite 3B | F90: Seattle | G90: WA | H90: 10049 | I90: USA | J90: (206) 555-0123 | K90: (206) 555-0132
A91: 90 | B91: Customer XBBVR | C91: Larsson, Katarina | D91: Owner/Marketing Assistant | E91: Keskuskatu 2345 | F91: Helsinki | H91: 10055 | I91: Finland | J91: 90-012 3456 | K91: 90-789 0123
A92: 91 | B92: Customer CCFIZ | C92: Conn, Steve | D92: Owner | E92: ul. Filtrowa 6789 | F92: Warszawa | H92: 10068 | I92: Poland | J92: (26) 234-5678 | K92: (26) 901-2345
A93: 91 | C93: Owner | D93: ul. Filtrowa 6789 | E93: Warszawa | G93: 10068 | H93: Poland | I93: (26) 234-5678 | J93: (26) 901-2345

Sheet Employee
A1: empid | B1: lastname | C1: firstname | D1: title | E1: titleofcourtesy | F1: birthdate | G1: hiredate | H1: address | I1: city | J1: region | K1: postalcode | L1: country | M1: phone | N1: extension | O1: photo | P1: notes | Q1: mgrid | R1: photopath
A2: 1 | B2: Davis | C2: Sara | D2: CEO | E2: Ms. | F2: 21527 | G2: 37377 | H2: 7890 - 20th Ave. E., Apt. 2A | I2: Seattle | J2: WA | K2: 10003 | L2: USA | M2: (206) 555-0101
A3: 2 | B3: Funk | C3: Don | D3: Vice President, Sales | E3: Dr. | F3: 22696 | G3: 37482 | H3: 9012 W. Capital Way | I3: Tacoma | J3: WA | K3: 10001 | L3: USA | M3: (206) 555-0100 | Q3: 1
A4: 3 | B4: Lew | C4: Judy | D4: Sales Manager | E4: Ms. | F4: 26906 | G4: 37347 | H4: 2345 Moss Bay Blvd. | I4: Kirkland | J4: WA | K4: 10007 | L4: USA | M4: (206) 555-0103 | Q4: 2
A5: 4 | B5: Peled | C5: Yael | D5: Sales Representative | E5: Mrs. | F5: 17429 | G5: 37744 | H5: 5678 Old Redmond Rd. | I5: Redmond | J5: WA | K5: 10009 | L5: USA | M5: (206) 555-0104 | Q5: 3
A6: 5 | B6: Buck | C6: Sven | D6: Sales Manager | E6: Mr. | F6: 23805 | G6: 37911 | H6: 8901 Garrett Hill | I6: London | K6: 10004 | L6: UK | M6: (71) 234-5678 | Q6: 2
A7: 6 | B7: Suurs | C7: Paul | D7: Sales Representative | E7: Mr. | F7: 26847 | G7: 37911 | H7: 3456 Coventry House, Miner Rd. | I7: London | K7: 10005 | L7: UK | M7: (71) 345-6789 | Q7: 5
A8: 7 | B8: King | C8: Russell | D8: Sales Representative | E8: Mr. | F8: 25717 | G8: 37988 | H8: 6789 Edgeham Hollow, Winchester Way | I8: London | K8: 10002 | L8: UK | M8: (71) 123-4567 | Q8: 5
A9: 8 | B9: Cameron | C9: Maria | D9: Sales Representative | E9: Ms. | F9: 24846 | G9: 38051 | H9: 4567 - 11th Ave. N.E. | I9: Seattle | J9: WA | K9: 10006 | L9: USA | M9: (206) 555-0102 | Q9: 3
A10: 9 | B10: Dolgopyatova | C10: Zoya | D10: Sales Representative | E10: Ms. | F10: 27786 | G10: 38306 | H10: 1234 Houndstooth Rd. | I10: London | K10: 10008 | L10: UK | M10: (71) 456-7890 | Q10: 5

Sheet Employee Territory
A1: employeeid | B1: territoryid
A2: 1 | B2: 6897
A3: 2 | B3: 19713
A4: 3 | B4: 1581
A5: 4 | B5: 1730
A6: 5 | B6: 1833
A7: 6 | B7: 2116
A8: 7 | B8: 2139
A9: 8 | B9: 2184
A10: 9 | B10: 40222
A11: 10 | B11: 30346
A12: 11 | B12: 31406
A13: 12 | B13: 32859
... A50: 49 | B50: 55439

Sheet Product
A1: productid | B1: productname | C1: supplierid | D1: categoryid | E1: quantityperunit | F1: unitprice | G1: unitsinstock | H1: unitsonorder | I1: reorderlevel | J1: discontinued
A2: 1 | B2: Product HHYDP | C2: 1 | D2: 1 | F2: 18 | J2: 0
A3: 2 | B3: Product RECZE | C3: 1 | D3: 1 | F3: 19 | J3: 0
A4: 3 | B4: Product IMEHJ | C4: 1 | D4: 2 | F4: 10 | J4: 0
A5: 4 | B5: Product KSBRM | C5: 2 | D5: 2 | F5: 22 | J5: 0
A6: 5 | B6: Product EPEIM | C6: 2 | D6: 2 | F6: 21.35 | J6: 1
A7: 6 | B7: Product VAIIV | C7: 3 | D7: 2 | F7: 25 | J7: 0
A8: 7 | B8: Product HMLNI | C8: 3 | D8: 7 | F8: 30 | J8: 0
A9: 8 | B9: Product WVJFP | C9: 3 | D9: 2 | F9: 40 | J9: 0
A10: 9 | B10: Product AOZBW | C10: 4 | D10: 6 | F10: 97 | J10: 1
A11: 10 | B11: Product YHXGE | C11: 4 | D11: 8 | F11: 31 | J11: 0
A12: 11 | B12: Product QMVUN | C12: 5 | D12: 4 | F12: 21 | J12: 0
A13: 12 | B13: Product OSFNS | C13: 5 | D13: 4 | F13: 38 | J13: 0
... A78: 77 | B78: Product LUNZZ | C78: 12 | D78: 2 | F78: 13 | J78: 0

Sheet Region
A1: regoinid | B1: regiondescription
A2: 1 | B2: Eastern
A3: 2 | B3: Western
A4: 3 | B4: Northern
A5: 4 | B5: Southern

Sheet Shipper
A1: shipperid | B1: companyname | C1: phone
A2: 1 | B2: Shipper GVSUA | C2: (503) 555-0137
A3: 2 | B3: Shipper ETYNR | C3: (425) 555-0136
A4: 3 | B4: Shipper ZHISN | C4: (415) 555-0138

Sheet Supplier
A1: supplierid | B1: companyname | C1: contactname | D1: contacttitle | E1: address | F1: city | G1: region | H1: postalcode | I1: country | J1: phone | K1: fax | L1: homepage
A2: 1 | B2: Supplier SWRXU | C2: Adolphi, Stephan | D2: Purchasing Manager | E2: 2345 Gilbert St. | F2: London | H2: 10023 | I2: UK | J2: (171) 456-7890
A3: 2 | B3: Supplier VHQZD | C3: Hance, Jim | D3: Order Administrator | E3: P.O. Box 5678 | F3: New Orleans | G3: LA | H3: 10013 | I3: USA | J3: (100) 555-0111
A4: 3 | B4: Supplier STUAZ | C4: Parovszky, Alfons | D4: Sales Representative | E4: 1234 Oxford Rd. | F4: Ann Arbor | G4: MI | H4: 10026 | I4: USA | J4: (313) 555-0109 | K4: (313) 555-0112
A5: 4 | B5: Supplier QOVFD | C5: Balázs, Erzsébet | D5: Marketing Manager | E5: 7890 Sekimai Musashino-shi | F5: Tokyo | H5: 10011 | I5: Japan | J5: (03) 6789-0123
A6: 5 | B6: Supplier EQPNC | C6: Holm, Michael | D6: Export Administrator | E6: Calle del Rosal 4567 | F6: Oviedo | G6: Asturias | H6: 10029 | I6: Spain | J6: (98) 123 45 67
A7: 6 | B7: Supplier QWUSF | C7: Popkova, Darya | D7: Marketing Representative | E7: 8901 Setsuko Chuo-ku | F7: Osaka | H7: 10028 | I7: Japan | J7: (06) 789-0123
A8: 7 | B8: Supplier GQRCV | C8: Ræbild, Jesper | D8: Marketing Manager | E8: 5678 Rose St. Moonie Ponds | F8: Melbourne | G8: Victoria | H8: 10018 | I8: Australia | J8: (03) 123-4567 | K8: (03) 456-7890
A9: 8 | B9: Supplier BWGYE | C9: Iallo, Lucio | D9: Sales Representative | E9: 9012 King's Way | F9: Manchester | H9: 10021 | I9: UK | J9: (161) 567-8901
A10: 9 | B10: Supplier QQYEU | C10: Basalik, Evan | D10: Sales Agent | E10: Kaloadagatan 4567 | F10: Göteborg | H10: 10022 | I10: Sweden | J10: 031-345 67 89 | K10: 031-678 90 12
A11: 10 | B11: Supplier UNAHG | C11: Barnett, Dave | D11: Marketing Manager | E11: Av. das Americanas 2345 | F11: Sao Paulo | H11: 10034 | I11: Brazil | J11: (11) 345 6789
A12: 11 | B12: Supplier ZPYVS | C12: Jain, Mukesh | D12: Sales Manager | E12: Tiergartenstraße 3456 | F12: Berlin | H12: 10016 | I12: Germany | J12: (010) 3456789
A13: 12 | B13: Supplier SVIYA | C13: Regev, Barak | D13: International Marketing Mgr. | E13: Bogenallee 9012 | F13: Frankfurt | H13: 10024 | I13: Germany | J13: (069) 234567
A14: 13 | B14: Supplier TEGSC | C14: Brehm, Peter | D14: Coordinator Foreign Markets | E14: Frahmredder 3456 | F14: Cuxhaven | H14: 10019 | I14: Germany | J14: (04721) 1234 | K14: (04721) 2345
A15: 14 | B15: Supplier KEREV | C15: Keil, Kendall | D15: Sales Representative | E15: Viale Dante, 6789 | F15: Ravenna | H15: 10015 | I15: Italy | J15: (0544) 56789 | K15: (0544) 34567
A16: 15 | B16: Supplier NZLIF | C16: Sałas-Szlejter, Karolina | D16: Marketing Manager | E16: Hatlevegen 1234 | F16: Sandvika | H16: 10025 | I16: Norway | J16: (0)9-012345
A17: 16 | B17: Supplier UHZRG | C17: Scholl, Thorsten | D17: Regional Account Rep. | E17: 8901 - 8th Avenue Suite 210 | F17: Bend | G17: OR | H17: 10035 | I17: USA | J17: (503) 555-0108
A18: 17 | B18: Supplier QZGUF | C18: Kleinerman, Christian | D18: Sales Representative | E18: Brovallavägen 0123 | F18: Stockholm | H18: 10033 | I18: Sweden | J18: 08-234 56 78
A19: 18 | B19: Supplier LVJUA | C19: Canel, Fabrice | D19: Sales Manager | E19: 3456, Rue des Francs-Bourgeois | F19: Paris | H19: 10031 | I19: France | J19: (1) 90.12.34.56 | K19: (1) 01.23.45.67
A20: 19 | B20: Supplier JDNUG | C20: Chapman, Greg | D20: Wholesale Account Agent | E20: Order Processing Dept. 7890 Paul Revere Blvd. | F20: Boston | G20: MA | H20: 10027 | I20: USA | J20: (617) 555-0110 | K20: (617) 555-0113
A21: 20 | B21: Supplier CIYNM | C21: Köszegi, Emília | D21: Owner | E21: 6789 Serangoon Loop, Suite #402 | F21: Singapore | H21: 10037 | I21: Singapore | J21: 012-3456
A22: 21 | B22: Supplier XOXZA | C22: Shakespear, Paul | D22: Sales Manager | E22: Lyngbysild Fiskebakken 9012 | F22: Lyngby | H22: 10012 | I22: Denmark | J22: 67890123 | K22: 78901234
A23: 22 | B23: Supplier FNUXM | C23: Skelly, Bonnie L. | D23: Accounting Manager | E23: Verkoop Rijnweg 8901 | F23: Zaandam | H23: 10014 | I23: Netherlands | J23: (12345) 8901 | K23: (12345) 5678
A24: 23 | B24: Supplier ELCRN | C24: LaMee, Brian | D24: Product Manager | E24: Valtakatu 1234 | F24: Lappeenranta | H24: 10032 | I24: Finland | J24: (953) 78901
A25: 24 | B25: Supplier JNNES | C25: Clark, Molly | D25: Sales Representative | E25: 6789 Prince Edward Parade Hunter's Hill | F25: Sydney | G25: NSW | H25: 10030 | I25: Australia | J25: (02) 234-5678 | K25: (02) 567-8901
A26: 25 | B26: Supplier ERVYZ | C26: Sprenger, Christof | D26: Marketing Manager | E26: 7890 Rue St. Laurent | F26: Montréal | G26: Québec | H26: 10017 | I26: Canada | J26: (514) 456-7890
A27: 26 | B27: Supplier ZWZDM | C27: Cunha, Gonçalo | D27: Order Administrator | E27: Via dei Gelsomini, 5678 | F27: Salerno | H27: 10020 | I27: Italy | J27: (089) 4567890 | K27: (089) 4567890
A28: 27 | B28: Supplier ZRYDZ | C28: Leoni, Alessandro | D28: Sales Manager | E28: 4567, rue H. Voiron | F28: Montceau | H28: 10036 | I28: France | J28: 89.01.23.45
A29: 28 | B29: Supplier OAVQT | C29: Teper, Jeff | D29: Sales Representative | E29: Bat. B 2345, rue des Alpes | F29: Annecy | H29: 10010 | I29: France | J29: 01.23.45.67 | K29: 89.01.23.45
A30: 29 | B30: Supplier OGLRK | C30: Walters, Rob | D30: Accounting Manager | E30: 0123 rue Chasseur | F30: Ste-Hyacinthe | G30: Québec | H30: 10009 | I30: Canada | J30: (514) 567-890 | K30: (514) 678-9012

Sheet Territory
A1: territoryid | B1: territorydescription | C1: regionid
A2: 1581 | B2: Westboro | C2: 1
A3: 1730 | B3: Bedford | C3: 1
A4: 1833 | B4: Georgetow | C4: 1
A5: 2116 | B5: Boston | C5: 1
A6: 2139 | B6: Cambridge | C6: 1
A7: 2184 | B7: Braintree | C7: 1
A8: 2903 | B8: Providence | C8: 1
A9: 3049 | B9: Hollis | C9: 3
A10: 3801 | B10: Portsmouth | C10: 3
A11: 6897 | B11: Wilton | C11: 1
A12: 7960 | B12: Morristown | C12: 1
A13: 8837 | B13: Edison | C13: 1
... A54: 98104 | B54: Seattle | C54: 2
